Project/formal/conv_pe_proof_cover/src/conv_pe.v
//==============================================================================
// conv_pe.v — Convolution Processing Element (Multi-Cycle MAC Unit)
//------------------------------------------------------------------------------
// Project : ELCT1005 PROJ02 — Pipelined RISC-V CPU with Conv-PE
// Replaces : Lab Week 1 verified black-box (re-implemented generically here)
//
// Function:
//   Performs one multiply-accumulate (MAC) step per custom-0 instruction:
//     init=0  →  acc ← acc + (operand_a × operand_b)   [accumulating MAC]
//     init=1  →  acc ←        operand_a × operand_b    [initialising MAC]
//   The result (current accumulator value) is written back to RD through
//   the WB 3:1 mux after CONV_LATENCY cycles.
//
// Parameters:
//   DATA_WIDTH    Width of each input operand (default 32).
//                 Operands are typically INT8/INT16 values sign- or zero-
//                 extended to DATA_WIDTH by preceding LB/LBU/LH/LHU/LW.
//   ACCUM_WIDTH   Width of the internal accumulator and conv_result output
//                 (default 32). Must be ≥ DATA_WIDTH. Overflow wraps modulo
//                 2^ACCUM_WIDTH (no saturation — document in project report).
//   CONV_LATENCY  Number of BUSY cycles per MAC instruction (default 4).
//                 Carried into the Phase 1 formal properties (CONV_STALL_COUNT,
//                 CONV_RESULT_STABLE). Must be ≥ 1.
//
// FSM (3 states — formally proven by CONV_FSM property in Phase 1):
//   IDLE  (2'b00) → waits for conv_start
//   BUSY  (2'b01) → counts CONV_LATENCY cycles, asserts conv_busy (stall)
//   DONE  (2'b10) → one-cycle pulse: asserts conv_done, latches result,
//                   returns to IDLE next cycle
//
// Pipeline interface:
//   conv_start  : single-cycle dispatch pulse from EX decode (opcode==custom-0)
//   init        : funct7[0] from the instruction word
//   operand_a   : RS1 value from ID/EX register (feature-map element)
//   operand_b   : RS2 value from ID/EX register (weight element)
//   conv_busy   : high during BUSY → freezes all pipeline stages
//   conv_done   : one-cycle high in DONE → EX/MEM register captures conv_result
//   conv_result : current accumulator value (valid when conv_done is high)
//   conv_status : raw FSM state for monitoring / formal properties
//
// Implementation notes:
//   - All resets are synchronous (active-low rst_n) — project-wide rule.
//   - No combinational paths from operands to outputs (fully registered MAC).
//   - The multiplier is registered at the start of BUSY, giving synthesis
//     freedom to pipeline the multiply across the CONV_LATENCY cycles.
//   - Overflow wraps modulo 2^ACCUM_WIDTH — project report must document this.
//   - No memory port: operands come from the register file exactly like ALU.
//==============================================================================
`timescale 1ns / 1ps
`default_nettype none

module conv_pe #(
    parameter integer DATA_WIDTH   = 32,   // operand width (INT8/16/32 extended)
    parameter integer ACCUM_WIDTH  = 32,   // accumulator / result width
    parameter integer CONV_LATENCY = 4     // busy cycles per MAC (≥ 1)
) (
    input  wire                    clk,
    input  wire                    rst_n,       // active-low synchronous reset

    // Dispatch interface (from EX stage decode)
    input  wire                    conv_start,  // 1-cycle high when custom-0 issued
    input  wire                    init,        // funct7[0]: 1=init MAC, 0=accum MAC

    // Operands (from ID/EX pipeline register)
    input  wire [DATA_WIDTH-1:0]   operand_a,   // RS1 — feature-map element
    input  wire [DATA_WIDTH-1:0]   operand_b,   // RS2 — weight element

    // Status & result
    output wire                    conv_busy,   // stall all pipeline stages
    output wire                    conv_done,   // 1-cycle pulse: result is valid
    output wire [ACCUM_WIDTH-1:0]  conv_result, // accumulator → WB mux
    output wire [1:0]              conv_status  // raw FSM state for formal props
);

    // =========================================================================
    // FSM state encoding
    // =========================================================================
    localparam [1:0] IDLE = 2'b00,
                     BUSY = 2'b01,
                     DONE = 2'b10;

    // =========================================================================
    // Internal registers
    // =========================================================================
    reg [1:0]              state_r;          // FSM state
    reg [ACCUM_WIDTH-1:0]  accum_r;          // running accumulator
    reg [ACCUM_WIDTH-1:0]  result_r;         // held result (stable through DONE)

    // Latency counter — counts up from 0 to CONV_LATENCY-1
    // Width is log2(CONV_LATENCY)+1 to avoid overflow for any parameter value
    localparam CTR_W = $clog2(CONV_LATENCY + 1) + 1;
    reg [CTR_W-1:0] cnt_r;

    // Registered copies of operands captured at the start of BUSY — isolates
    // the MAC from combinational glitch on operand_a/b after ID/EX moves on.
    reg [DATA_WIDTH-1:0]   op_a_r;
    reg [DATA_WIDTH-1:0]   op_b_r;
    reg                    init_r;           // registered init flag

    // =========================================================================
    // MAC compute — registered product, accumulates into accum_r.
    // Using ACCUM_WIDTH-wide multiply (lower ACCUM_WIDTH bits of the product).
    // Overflow wraps modulo 2^ACCUM_WIDTH — document in project report.
    // =========================================================================
    wire [ACCUM_WIDTH-1:0] product;
    assign product = op_a_r[ACCUM_WIDTH-1:0] * op_b_r[ACCUM_WIDTH-1:0];

    // =========================================================================
    // FSM + datapath — single synchronous always block
    // =========================================================================
    always @(posedge clk) begin
        if (!rst_n) begin
            // ---- Synchronous reset -------------------------------------------
            state_r  <= IDLE;
            accum_r  <= {ACCUM_WIDTH{1'b0}};
            result_r <= {ACCUM_WIDTH{1'b0}};
            cnt_r    <= {CTR_W{1'b0}};
            op_a_r   <= {DATA_WIDTH{1'b0}};
            op_b_r   <= {DATA_WIDTH{1'b0}};
            init_r   <= 1'b0;
        end else begin
            case (state_r)

                // ---- IDLE ---------------------------------------------------
                // Wait for a dispatch pulse. On conv_start, capture operands
                // and transition to BUSY.
                IDLE: begin
                    if (conv_start) begin
                        op_a_r  <= operand_a;
                        op_b_r  <= operand_b;
                        init_r  <= init;
                        cnt_r   <= {CTR_W{1'b0}};
                        state_r <= BUSY;
                    end
                end

                // ---- BUSY ---------------------------------------------------
                // Assert conv_busy (stall) for exactly CONV_LATENCY cycles.
                // On the last cycle compute the MAC result and move to DONE.
                BUSY: begin
                    if (cnt_r == {{(CTR_W-1){1'b0}}, 1'b1} * (CONV_LATENCY - 1)) begin
                        // Final busy cycle — compute and latch result
                        if (init_r)
                            result_r <= product;                  // init:  acc = a*b
                        else
                            result_r <= accum_r + product;        // accum: acc += a*b

                        state_r <= DONE;
                    end else begin
                        cnt_r <= cnt_r + 1'b1;
                    end
                end

                // ---- DONE ---------------------------------------------------
                // Single-cycle pulse: conv_done is high, result is stable.
                // Update the persistent accumulator and return to IDLE.
                DONE: begin
                    accum_r <= result_r;   // keep accumulator updated
                    state_r <= IDLE;
                end

                // ---- Default (unreachable — CONV_FSM formal prop proves this)
                default: state_r <= IDLE;

            endcase
        end
    end

    // =========================================================================
    // Output assignments (combinational from state register)
    // =========================================================================
    assign conv_busy   = (state_r == BUSY);
    assign conv_done   = (state_r == DONE);
    assign conv_result = result_r;          // stable from DONE until next conv_start
    assign conv_status = state_r;

endmodule

`default_nettype wire

Project/tb_conv_pe.v
//==============================================================================
// tb_conv_pe.v — Self-Checking Directed Testbench for conv_pe
//------------------------------------------------------------------------------
// Tests:
//   TC1  — Reset behaviour: all outputs low/zero after rst_n de-asserted
//   TC2  — Init MAC (init=1): acc = a * b, conv_busy for exactly CONV_LATENCY
//           cycles, conv_done for exactly 1 cycle, correct result
//   TC3  — Accumulating MAC (init=0): acc += a * b (chains 3 MACs)
//   TC4  — Re-init mid-sequence (init=1 resets accumulator)
//   TC5  — Back-to-back instructions with NOPs between (pipeline stall model)
//   TC6  — Zero operand: result must be 0 on init, unchanged on accum
//   TC7  — conv_busy deasserted exactly on DONE, not before / not after
//==============================================================================
`timescale 1ns / 1ps

module tb_conv_pe;

    // ---- Parameters (must match DUT instantiation) -------------------------
    localparam DATA_WIDTH   = 32;
    localparam ACCUM_WIDTH  = 32;
    localparam CONV_LATENCY = 4;
    localparam CLK_PERIOD   = 10;   // 10 ns = 100 MHz

    // ---- DUT ports ---------------------------------------------------------
    reg                    clk;
    reg                    rst_n;
    reg                    conv_start;
    reg                    init;
    reg  [DATA_WIDTH-1:0]  operand_a;
    reg  [DATA_WIDTH-1:0]  operand_b;
    wire                   conv_busy;
    wire                   conv_done;
    wire [ACCUM_WIDTH-1:0] conv_result;
    wire [1:0]             conv_status;

    // ---- DUT instantiation -------------------------------------------------
    conv_pe #(
        .DATA_WIDTH   (DATA_WIDTH),
        .ACCUM_WIDTH  (ACCUM_WIDTH),
        .CONV_LATENCY (CONV_LATENCY)
    ) dut (
        .clk         (clk),
        .rst_n       (rst_n),
        .conv_start  (conv_start),
        .init        (init),
        .operand_a   (operand_a),
        .operand_b   (operand_b),
        .conv_busy   (conv_busy),
        .conv_done   (conv_done),
        .conv_result (conv_result),
        .conv_status (conv_status)
    );

    // ---- Clock generator ---------------------------------------------------
    initial clk = 0;
    always #(CLK_PERIOD/2) clk = ~clk;

    // ---- Test utilities ----------------------------------------------------
    integer pass_count, fail_count;

    task check;
        input [63:0] got;
        input [63:0] expected;
        input [127:0] label;
        begin
            if (got === expected) begin
                $display("  PASS  %-40s  got=%0d", label, got);
                pass_count = pass_count + 1;
            end else begin
                $display("  FAIL  %-40s  got=%0d  expected=%0d", label, got, expected);
                fail_count = fail_count + 1;
            end
        end
    endtask

    // Issue one MAC instruction and wait until DONE returns to IDLE.
    // Returns the conv_result captured at conv_done.
    // Also checks that conv_busy lasted exactly CONV_LATENCY cycles.
    task issue_mac;
        input [DATA_WIDTH-1:0]  a;
        input [DATA_WIDTH-1:0]  b;
        input                   i_init;
        output [ACCUM_WIDTH-1:0] result_out;
        integer busy_count;
        begin
            busy_count = 0;
            @(negedge clk);         // set up inputs before rising edge
            conv_start = 1'b1;
            operand_a  = a;
            operand_b  = b;
            init       = i_init;
            @(negedge clk);         // one cycle: conv_start seen, enter BUSY
            conv_start = 1'b0;

            // Count BUSY cycles
            while (conv_busy) begin
                busy_count = busy_count + 1;
                @(negedge clk);
            end

            // Should be in DONE now (conv_busy just went low)
            result_out = conv_result;

            check(busy_count, CONV_LATENCY, "busy_count == CONV_LATENCY");

            @(negedge clk);         // DONE → IDLE transition
        end
    endtask

    // ---- Stimulus ----------------------------------------------------------
    integer i;
    reg [ACCUM_WIDTH-1:0] r;
    reg [ACCUM_WIDTH-1:0] expected_acc;

    initial begin
        $dumpfile("tb_conv_pe.vcd");
        $dumpvars(0, tb_conv_pe);

        pass_count = 0;
        fail_count = 0;

        // Default inputs
        rst_n      = 1'b0;
        conv_start = 1'b0;
        init       = 1'b0;
        operand_a  = 32'h0;
        operand_b  = 32'h0;

        // ---- TC1 Reset -------------------------------------------------------
        $display("\n=== TC1: Reset behaviour ===");
        repeat (3) @(posedge clk);
        #1;
        check(conv_busy,   0, "conv_busy == 0 during reset");
        check(conv_done,   0, "conv_done == 0 during reset");
        check(conv_result, 0, "conv_result == 0 during reset");
        check(conv_status, 2'b00, "conv_status == IDLE during reset");

        @(negedge clk);
        rst_n = 1'b1;
        @(negedge clk);
        check(conv_busy,   0, "conv_busy == 0 after reset release");
        check(conv_status, 2'b00, "conv_status == IDLE after reset release");

        // ---- TC2 Init MAC ----------------------------------------------------
        $display("\n=== TC2: Init MAC (init=1), a=5, b=6 => result=30 ===");
        issue_mac(32'd5, 32'd6, 1'b1, r);
        check(r, 32'd30, "init MAC: 5*6 = 30");
        check(conv_done, 0, "conv_done low after DONE→IDLE");
        check(conv_busy, 0, "conv_busy low after DONE→IDLE");

        // ---- TC3 Accumulating MACs ------------------------------------------
        $display("\n=== TC3: Accumulate 3 MACs: 3*4 + 2*5 + 1*7 = 12+10+7 = 29 ===");
        // First MAC initialises (init=1)
        issue_mac(32'd3, 32'd4, 1'b1, r);
        check(r, 32'd12, "accum chain step1: 3*4 = 12");

        // Second MAC accumulates
        issue_mac(32'd2, 32'd5, 1'b0, r);
        check(r, 32'd22, "accum chain step2: 12 + 2*5 = 22");

        // Third MAC accumulates
        issue_mac(32'd1, 32'd7, 1'b0, r);
        check(r, 32'd29, "accum chain step3: 22 + 1*7 = 29");

        // ---- TC4 Re-init mid-sequence ----------------------------------------
        $display("\n=== TC4: Re-init with init=1 clears previous accumulator ===");
        issue_mac(32'd10, 32'd10, 1'b1, r);
        check(r, 32'd100, "re-init: 10*10 = 100 (not 100+29)");

        // ---- TC5 Back-to-back with 0-cycle gap (NOPs handled by pipeline) ---
        $display("\n=== TC5: Two back-to-back MACs ===");
        issue_mac(32'd7, 32'd3, 1'b1, r);
        check(r, 32'd21, "back-to-back step1: 7*3 = 21");
        issue_mac(32'd4, 32'd4, 1'b0, r);
        check(r, 32'd37, "back-to-back step2: 21 + 4*4 = 37");

        // ---- TC6 Zero operand -----------------------------------------------
        $display("\n=== TC6: Zero operand ===");
        issue_mac(32'd0, 32'd99, 1'b1, r);
        check(r, 32'd0, "init with a=0: 0*99 = 0");
        issue_mac(32'd0, 32'd99, 1'b0, r);
        check(r, 32'd0, "accum with a=0: 0 + 0*99 = 0");

        // ---- TC7 conv_done width (exactly 1 cycle) --------------------------
        $display("\n=== TC7: conv_done is exactly 1 cycle wide ===");
        @(negedge clk);
        conv_start = 1'b1;
        operand_a  = 32'd2;
        operand_b  = 32'd3;
        init       = 1'b1;
        @(negedge clk);
        conv_start = 1'b0;

        // Wait until conv_done rises
        while (!conv_done) @(negedge clk);
        check(conv_done, 1, "conv_done asserted");

        @(negedge clk);
        check(conv_done, 0, "conv_done deasserted after 1 cycle");
        check(conv_busy, 0, "conv_busy low after DONE");

        // ---- Final summary ---------------------------------------------------
        $display("\n====================================================");
        $display("  Results: %0d PASS,  %0d FAIL", pass_count, fail_count);
        $display("====================================================\n");

        if (fail_count == 0)
            $display("ALL TESTS PASSED");
        else
            $display("FAILURES DETECTED — review output above");

        $finish;
    end

    // Watchdog — abort if stuck
    initial begin
        #(CLK_PERIOD * 2000);
        $display("WATCHDOG TIMEOUT");
        $finish;
    end

endmodule

Project/rtl/tb/results/tb_conv_pe.vcd
$date
	Tue May  5 10:31:53 2026
$end
$version
	Icarus Verilog
$end
$timescale
	1ps
$end
$scope module tb_conv_pe $end
$var wire 2 ! conv_status [1:0] $end
$var wire 32 " conv_result [31:0] $end
$var wire 1 # conv_done $end
$var wire 1 $ conv_busy $end
$var parameter 32 % ACCUM_WIDTH $end
$var parameter 32 & CLK_PERIOD $end
$var parameter 32 ' CONV_LATENCY $end
$var parameter 32 ( DATA_WIDTH $end
$var reg 1 ) clk $end
$var reg 1 * conv_start $end
$var reg 1 + init $end
$var reg 32 , operand_a [31:0] $end
$var reg 32 - operand_b [31:0] $end
$var reg 32 . r [31:0] $end
$var reg 1 / rst_n $end
$var integer 32 0 fail_count [31:0] $end
$var integer 32 1 pass_count [31:0] $end
$scope module dut $end
$var wire 1 ) clk $end
$var wire 32 2 conv_result [31:0] $end
$var wire 1 * conv_start $end
$var wire 2 3 conv_status [1:0] $end
$var wire 1 + init $end
$var wire 32 4 operand_a [31:0] $end
$var wire 32 5 operand_b [31:0] $end
$var wire 1 / rst_n $end
$var wire 32 6 product [31:0] $end
$var wire 1 # conv_done $end
$var wire 1 $ conv_busy $end
$var parameter 32 7 ACCUM_WIDTH $end
$var parameter 2 8 BUSY $end
$var parameter 32 9 CONV_LATENCY $end
$var parameter 33 : CTR_W $end
$var parameter 32 ; DATA_WIDTH $end
$var parameter 2 < DONE $end
$var parameter 2 = IDLE $end
$var reg 32 > accum_r [31:0] $end
$var reg 4 ? cnt_r [3:0] $end
$var reg 1 @ init_r $end
$var reg 32 A op_a_r [31:0] $end
$var reg 32 B op_b_r [31:0] $end
$var reg 32 C result_r [31:0] $end
$var reg 2 D state_r [1:0] $end
$upscope $end
$scope task check $end
$var reg 64 E expected [63:0] $end
$var reg 64 F got [63:0] $end
$var reg 128 G label [127:0] $end
$upscope $end
$scope task issue_mac $end
$var reg 32 H a [31:0] $end
$var reg 32 I b [31:0] $end
$var reg 1 J i_init $end
$var reg 32 K result_out [31:0] $end
$var integer 32 L busy_count [31:0] $end
$upscope $end
$upscope $end
$enddefinitions $end
$comment Show the parameter values. $end
$dumpall
b0 =
b10 <
b100000 ;
b100 :
b100 9
b1 8
b100000 7
b100000 (
b100 '
b1010 &
b100000 %
$end
#0
$dumpvars
bx L
bx K
xJ
bx I
bx H
bx G
bx F
bx E
bx D
bx C
bx B
bx A
x@
bx ?
bx >
bx 6
b0 5
b0 4
bx 3
bx 2
b0 1
b0 0
0/
bx .
b0 -
b0 ,
0+
0*
0)
x$
x#
bx "
bx !
$end
#5000
0@
b0 6
b0 B
b0 A
b0 ?
b0 "
b0 2
b0 C
b0 >
0$
0#
b0 !
b0 3
b0 D
1)
#10000
0)
#15000
1)
#20000
0)
#25000
1)
#26000
b100 1
b1000100010011000100010100100000011001000111010101110010011010010110111001100111001000000111001001100101011100110110010101110100 G
b0 E
b0 F
#30000
1/
0)
#35000
1)
#40000
b0 L
1J
b110 I
b101 H
b110 1
b1100101011100100010000001110010011001010111001101100101011101000010000001110010011001010110110001100101011000010111001101100101 G
0)
#45000
1)
#50000
1+
b110 -
b110 5
b101 ,
b101 4
1*
0)
#55000
1$
b1 !
b1 3
b1 D
1@
b11110 6
b110 B
b101 A
1)
#60000
b1 L
0*
0)
#65000
b1 ?
1)
#70000
b10 L
0)
#75000
b10 ?
1)
#80000
b11 L
0)
#85000
b11 ?
1)
#90000
b100 L
0)
#95000
0$
1#
b10 !
b10 3
b10 D
b11110 "
b11110 2
b11110 C
1)
#100000
b111 1
b100000001111010011110100100000010000110100111101001110010101100101111101001100010000010101010001000101010011100100001101011001 G
b100 E
b100 F
b11110 K
0)
#105000
0#
b0 !
b0 3
b0 D
b11110 >
1)
#110000
b0 L
b100 I
b11 H
b1010 1
b1100110011101000110010101110010001000000100010001001111010011100100010111100010100001101001001001001001010001000100110001000101 G
b0 E
b0 F
b11110 .
0)
#115000
1)
#120000
b100 -
b100 5
b11 ,
b11 4
1*
0)
#125000
1$
b1 !
b1 3
b1 D
b0 ?
b100 B
b1100 6
b11 A
1)
#130000
b1 L
0*
0)
#135000
b1 ?
1)
#140000
b10 L
0)
#145000
b10 ?
1)
#150000
b11 L
0)
#155000
b11 ?
1)
#160000
b100 L
0)
#165000
0$
1#
b10 !
b10 3
b10 D
b1100 "
b1100 2
b1100 C
1)
#170000
b1011 1
b100000001111010011110100100000010000110100111101001110010101100101111101001100010000010101010001000101010011100100001101011001 G
b100 E
b100 F
b1100 K
0)
#175000
0#
b0 !
b0 3
b0 D
b1100 >
1)
#180000
b0 L
0J
b101 I
b10 H
b1100 1
b100000011100110111010001100101011100000011000100111010001000000011001100101010001101000010000000111101001000000011000100110010 G
b1100 E
b1100 F
b1100 .
0)
#185000
1)
#190000
0+
b101 -
b101 5
b10 ,
b10 4
1*
0)
#195000
1$
b1 !
b1 3
b1 D
b0 ?
0@
b101 B
b1010 6
b10 A
1)
#200000
b1 L
0*
0)
#205000
b1 ?
1)
#210000
b10 L
0)
#215000
b10 ?
1)
#220000
b11 L
0)
#225000
b11 ?
1)
#230000
b100 L
0)
#235000
0$
1#
b10 !
b10 3
b10 D
b10110 "
b10110 2
b10110 C
1)
#240000
b1101 1
b100000001111010011110100100000010000110100111101001110010101100101111101001100010000010101010001000101010011100100001101011001 G
b100 E
b100 F
b10110 K
0)
#245000
0#
b0 !
b0 3
b0 D
b10110 >
1)
#250000
b0 L
b111 I
b1 H
b1110 1
b110010001110100010000000110001001100100010000000101011001000000011001000101010001101010010000000111101001000000011001000110010 G
b10110 E
b10110 F
b10110 .
0)
#255000
1)
#260000
b111 -
b111 5
b1 ,
b1 4
1*
0)
#265000
1$
b1 !
b1 3
b1 D
b0 ?
b111 B
b111 6
b1 A
1)
#270000
b1 L
0*
0)
#275000
b1 ?
1)
#280000
b10 L
0)
#285000
b10 ?
1)
#290000
b11 L
0)
#295000
b11 ?
1)
#300000
b100 L
0)
#305000
0$
1#
b10 !
b10 3
b10 D
b11101 "
b11101 2
b11101 C
1)
#310000
b1111 1
b100000001111010011110100100000010000110100111101001110010101100101111101001100010000010101010001000101010011100100001101011001 G
b100 E
b100 F
b11101 K
0)
#315000
0#
b0 !
b0 3
b0 D
b11101 >
1)
#320000
b0 L
1J
b1010 I
b1010 H
b10000 1
b110011001110100010000000110010001100100010000000101011001000000011000100101010001101110010000000111101001000000011001000111001 G
b11101 E
b11101 F
b11101 .
0)
#325000
1)
#330000
1+
b1010 -
b1010 5
b1010 ,
b1010 4
1*
0)
#335000
1$
b1 !
b1 3
b1 D
b0 ?
1@
b1010 B
b1100100 6
b1010 A
1)
#340000
b1 L
0*
0)
#345000
b1 ?
1)
#350000
b10 L
0)
#355000
b10 ?
1)
#360000
b11 L
0)
#365000
b11 ?
1)
#370000
b100 L
0)
#375000
0$
1#
b10 !
b10 3
b10 D
b1100100 "
b1100100 2
b1100100 C
1)
#380000
b10001 1
b100000001111010011110100100000010000110100111101001110010101100101111101001100010000010101010001000101010011100100001101011001 G
b100 E
b100 F
b1100100 K
0)
#385000
0#
b0 !
b0 3
b0 D
b1100100 >
1)
#390000
b0 L
b11 I
b111 H
b10010 1
b110001001100000011000000100000001010000110111001101111011101000010000000110001001100000011000000101011001100100011100100101001 G
b1100100 E
b1100100 F
b1100100 .
0)
#395000
1)
#400000
b11 -
b11 5
b111 ,
b111 4
1*
0)
#405000
1$
b1 !
b1 3
b1 D
b0 ?
b11 B
b10101 6
b111 A
1)
#410000
b1 L
0*
0)
#415000
b1 ?
1)
#420000
b10 L
0)
#425000
b10 ?
1)
#430000
b11 L
0)
#435000
b11 ?
1)
#440000
b100 L
0)
#445000
0$
1#
b10 !
b10 3
b10 D
b10101 "
b10101 2
b10101 C
1)
#450000
b10011 1
b100000001111010011110100100000010000110100111101001110010101100101111101001100010000010101010001000101010011100100001101011001 G
b100 E
b100 F
b10101 K
0)
#455000
0#
b0 !
b0 3
b0 D
b10101 >
1)
#460000
b0 L
0J
b100 I
b100 H
b10100 1
b100000011100110111010001100101011100000011000100111010001000000011011100101010001100110010000000111101001000000011001000110001 G
b10101 E
b10101 F
b10101 .
0)
#465000
1)
#470000
0+
b100 -
b100 5
b100 ,
b100 4
1*
0)
#475000
1$
b1 !
b1 3
b1 D
b0 ?
0@
b100 B
b10000 6
b100 A
1)
#480000
b1 L
0*
0)
#485000
b1 ?
1)
#490000
b10 L
0)
#495000
b10 ?
1)
#500000
b11 L
0)
#505000
b11 ?
1)
#510000
b100 L
0)
#515000
0$
1#
b10 !
b10 3
b10 D
b100101 "
b100101 2
b100101 C
1)
#520000
b10101 1
b100000001111010011110100100000010000110100111101001110010101100101111101001100010000010101010001000101010011100100001101011001 G
b100 E
b100 F
b100101 K
0)
#525000
0#
b0 !
b0 3
b0 D
b100101 >
1)
#530000
b0 L
1J
b1100011 I
b0 H
b10110 1
b110010001110100010000000110010001100010010000000101011001000000011010000101010001101000010000000111101001000000011001100110111 G
b100101 E
b100101 F
b100101 .
0)
#535000
1)
#540000
1+
b1100011 -
b1100011 5
b0 ,
b0 4
1*
0)
#545000
1$
b1 !
b1 3
b1 D
b0 ?
1@
b1100011 B
b0 6
b0 A
1)
#550000
b1 L
0*
0)
#555000
b1 ?
1)
#560000
b10 L
0)
#565000
b10 ?
1)
#570000
b11 L
0)
#575000
b11 ?
1)
#580000
b100 L
0)
#585000
0$
1#
b10 !
b10 3
b10 D
b0 "
b0 2
b0 C
1)
#590000
b10111 1
b100000001111010011110100100000010000110100111101001110010101100101111101001100010000010101010001000101010011100100001101011001 G
b100 E
b100 F
b0 K
0)
#595000
0#
b0 !
b0 3
b0 D
b0 >
1)
#600000
b0 L
0J
b11000 1
b1110100011010000010000001100001001111010011000000111010001000000011000000101010001110010011100100100000001111010010000000110000 G
b0 E
b0 F
b0 .
0)
#605000
1)
#610000
0+
1*
0)
#615000
1$
b1 !
b1 3
b1 D
b0 ?
0@
1)
#620000
b1 L
0*
0)
#625000
b1 ?
1)
#630000
b10 L
0)
#635000
b10 ?
1)
#640000
b11 L
0)
#645000
b11 ?
1)
#650000
b100 L
0)
#655000
0$
1#
b10 !
b10 3
b10 D
1)
#660000
b11001 1
b100000001111010011110100100000010000110100111101001110010101100101111101001100010000010101010001000101010011100100001101011001 G
b100 E
b100 F
0)
#665000
0#
b0 !
b0 3
b0 D
1)
#670000
b11010 1
b111101001100000011101000100000001100000010000000101011001000000011000000101010001110010011100100100000001111010010000000110000 G
b0 E
b0 F
0)
#675000
1)
#680000
1+
b11 -
b11 5
b10 ,
b10 4
1*
0)
#685000
1$
b1 !
b1 3
b1 D
b0 ?
1@
b11 B
b110 6
b10 A
1)
#690000
0*
0)
#695000
b1 ?
1)
#700000
0)
#705000
b10 ?
1)
#710000
0)
#715000
b11 ?
1)
#720000
0)
#725000
0$
1#
b10 !
b10 3
b10 D
b110 "
b110 2
b110 C
1)
#730000
b11011 1
b1101110011101100101111101100100011011110110111001100101001000000110000101110011011100110110010101110010011101000110010101100100 G
b1 E
b1 F
0)
#735000
0#
b0 !
b0 3
b0 D
b110 >
1)
#740000
b11101 1
b1111001001000000110110001101111011101110010000001100001011001100111010001100101011100100010000001000100010011110100111001000101 G
b0 E
b0 F
0)
