Project/formal/riscv_safety_prove/src/if_stage.v
//==============================================================================
// if_stage.v — Instruction Fetch Stage
//------------------------------------------------------------------------------
// Project : ELCT1005 PROJ02 — Pipelined RISC-V CPU with Conv-PE
//
// Responsibilities:
//   1. Hold and update the Program Counter (PC) register
//   2. Select the next PC via a 3-way mux:
//        pc_src = 2'b00  ->  PC + 4          (sequential, default)
//        pc_src = 2'b01  ->  branch_target   (taken branch from EX)
//        pc_src = 2'b10  ->  jump_target     (JAL / JALR from EX)
//   3. Drive imem with the current PC (fetch address)
//   4. Output a PC-delay register (pc_if_o) aligned with imem's registered
//      instruction output so the IF/ID pipeline register in riscv_top.v
//      receives a matched (PC, instruction) pair.
//   5. Honour stall (Conv-PE busy) and flush (branch/jump taken) controls.
//
// Timing note — synchronous imem:
//   imem registers its output on the rising edge, so the instruction word
//   arriving at instr_i in cycle N was requested by the address driven in
//   cycle N-1.  To keep (PC, instruction) aligned at the IF/ID boundary we
//   maintain pc_if_r, a one-cycle-delayed copy of pc_reg.  riscv_top.v
//   latches both pc_if_o and instr_i into the IF/ID pipeline register on
//   the same rising edge.
//
// Stall behaviour (conv_busy):
//   Both pc_reg and pc_if_r are frozen — the same address keeps driving imem
//   so the same instruction word re-appears next cycle and is re-latched into
//   the IF/ID register.
//
// Flush behaviour (branch / JAL / JALR taken):
//   pc_reg is loaded with the target address.
//   pc_if_r is loaded with PC_NOP (0x00000000) so the IF/ID register latches
//   a NOP-aligned PC, and instr_i will carry the NOP that imem outputs when
//   addressed at 0 (imem initialises all locations to NOP).
//   The flush of the ID/EX register (to hold a bubble/NOP) is handled in
//   riscv_top.v — not here.
//
// Ports:
//   Inputs:
//     clk, rst_n        — global clock and active-low synchronous reset
//     stall_i           — freeze PC when Conv-PE is BUSY
//     flush_i           — invalidate current fetch (branch/jump taken)
//     pc_src_i [1:0]    — next-PC select (see above)
//     branch_target_i   — branch target from EX stage
//     jump_target_i     — JAL/JALR target from EX stage
//     instr_i [31:0]    — registered instruction word from imem
//   Outputs:
//     pc_fetch_o [31:0] — PC driven to imem address port (current pc_reg)
//     pc_if_o    [31:0] — PC aligned with instr_i (one-cycle delayed)
//     pc_plus4_o [31:0] — PC+4 (forwarded to ID stage for JAL/JALR link)
//==============================================================================
`timescale 1ns / 1ps
`default_nettype none

module if_stage (
    input  wire        clk,
    input  wire        rst_n,

    // Pipeline controls
    input  wire        stall_i,           // freeze (Conv-PE busy)
    input  wire        flush_i,           // invalidate fetch (branch/jump taken)

    // Next-PC select and targets
    input  wire [1:0]  pc_src_i,          // 00=PC+4, 01=branch, 10=jump
    input  wire [31:0] branch_target_i,
    input  wire [31:0] jump_target_i,

    // Instruction word from imem (synchronous / registered output)
    input  wire [31:0] instr_i,

    // Outputs to imem and IF/ID pipeline register
    output wire [31:0] pc_fetch_o,        // -> imem address port
    output wire [31:0] pc_if_o,           // -> IF/ID register (matched to instr)
    output wire [31:0] pc_plus4_o         // -> IF/ID register (link address)
);

    // =========================================================================
    // PC register — drives imem address
    // =========================================================================
    reg [31:0] pc_reg;

    // Next-PC combinational mux
    reg [31:0] next_pc;
    always @* begin
        case (pc_src_i)
            2'b01:   next_pc = branch_target_i;
            2'b10:   next_pc = jump_target_i;
            default: next_pc = pc_reg + 32'd4;   // sequential
        endcase
    end

    always @(posedge clk) begin
        if (!rst_n)
            pc_reg <= 32'h00000000;
        else if (flush_i)
            pc_reg <= next_pc;          // load target, discards in-flight fetch
        else if (!stall_i)
            pc_reg <= next_pc;
        // stall_i=1 and no flush: pc_reg holds (same addr re-driven to imem)
    end

    // =========================================================================
    // PC-delay register — aligns PC with imem's registered instruction output
    // =========================================================================
    localparam PC_NOP = 32'h00000000;   // bubble PC written on flush

    reg [31:0] pc_if_r;

    always @(posedge clk) begin
        if (!rst_n)
            pc_if_r <= PC_NOP;
        else if (flush_i)
            pc_if_r <= PC_NOP;          // bubble: instr_i will be a NOP
        else if (!stall_i)
            pc_if_r <= pc_reg;          // capture the PC that just drove imem
        // stall: pc_if_r holds (IF/ID register will also be frozen in top)
    end

    // =========================================================================
    // Outputs
    // =========================================================================
    assign pc_fetch_o = pc_reg;
    assign pc_if_o    = pc_if_r;
    assign pc_plus4_o = pc_if_r + 32'd4;   // PC+4 for JAL/JALR link value

endmodule

`default_nettype wire

Project/rtl/tb/tb_if_stage.v
//==============================================================================
// tb_if_stage.v — Self-Checking Testbench for if_stage
//------------------------------------------------------------------------------
// Tests:
//   TC1 — Reset: PC starts at 0x00000000 after reset
//   TC2 — Sequential fetch: PC increments by 4 each cycle
//   TC3 — pc_plus4_o tracks pc_if_o + 4
//   TC4 — Branch taken: PC jumps to branch_target, bubble inserted
//   TC5 — Jump taken (JAL/JALR): PC jumps to jump_target, bubble inserted
//   TC6 — Stall: PC and pc_if frozen while stall_i=1
//   TC7 — Flush during stall: flush overrides stall, loads target
//   TC8 — pc_fetch_o and pc_if_o are one cycle apart (alignment check)
//==============================================================================
`timescale 1ns / 1ps

module tb_if_stage;

    localparam CLK_PERIOD = 10;

    // ---- DUT ports ----------------------------------------------------------
    reg         clk, rst_n, stall_i, flush_i;
    reg  [1:0]  pc_src_i;
    reg  [31:0] branch_target_i, jump_target_i;
    reg  [31:0] instr_i;           // driven by test (models imem registered output)

    wire [31:0] pc_fetch_o;
    wire [31:0] pc_if_o;
    wire [31:0] pc_plus4_o;

    // ---- DUT ----------------------------------------------------------------
    if_stage dut (
        .clk              (clk),
        .rst_n            (rst_n),
        .stall_i          (stall_i),
        .flush_i          (flush_i),
        .pc_src_i         (pc_src_i),
        .branch_target_i  (branch_target_i),
        .jump_target_i    (jump_target_i),
        .instr_i          (instr_i),
        .pc_fetch_o       (pc_fetch_o),
        .pc_if_o          (pc_if_o),
        .pc_plus4_o       (pc_plus4_o)
    );

    // ---- Clock --------------------------------------------------------------
    initial clk = 0;
    always #(CLK_PERIOD/2) clk = ~clk;

    // ---- Helpers ------------------------------------------------------------
    integer pass_count, fail_count;

    task check32;
        input [31:0] got;
        input [31:0] expected;
        input [255:0] label;
        begin
            if (got === expected) begin
                $display("  PASS  %-48s  got=0x%08h", label, got);
                pass_count = pass_count + 1;
            end else begin
                $display("  FAIL  %-48s  got=0x%08h  exp=0x%08h",
                         label, got, expected);
                fail_count = fail_count + 1;
            end
        end
    endtask

    // Advance one cycle with current settings, then sample outputs
    task tick;
        begin
            @(posedge clk); #1;
        end
    endtask

    // =========================================================================
    initial begin
        $dumpfile("tb_if_stage.vcd");
        $dumpvars(0, tb_if_stage);
        pass_count = 0; fail_count = 0;

        // Default inputs
        rst_n           = 1'b0;
        stall_i         = 1'b0;
        flush_i         = 1'b0;
        pc_src_i        = 2'b00;
        branch_target_i = 32'h0000_0000;
        jump_target_i   = 32'h0000_0000;
        instr_i         = 32'h0000_0013;   // NOP

        // =====================================================================
        // TC1 — Reset
        // =====================================================================
        $display("\n=== TC1: Reset ===");
        repeat(2) @(posedge clk); #1;
        check32(pc_fetch_o, 32'h0000_0000, "pc_fetch_o = 0 during reset");
        check32(pc_if_o,    32'h0000_0000, "pc_if_o    = 0 during reset");

        // Release reset
        @(negedge clk); rst_n = 1'b1;

        // =====================================================================
        // TC2 — Sequential fetch: PC+4 every cycle
        // =====================================================================
        $display("\n=== TC2: Sequential fetch ===");
        // After reset release, PC = 0 fetching addr 0
        // Each tick: pc_fetch_o advances by 4
        tick; check32(pc_fetch_o, 32'h0000_0004, "pc_fetch after 1 tick = 0x4");
        tick; check32(pc_fetch_o, 32'h0000_0008, "pc_fetch after 2 ticks = 0x8");
        tick; check32(pc_fetch_o, 32'h0000_000C, "pc_fetch after 3 ticks = 0xC");

        // pc_if_o lags pc_fetch_o by one cycle
        // After 3 ticks: pc_fetch=0xC, pc_if should be 0x8
        check32(pc_if_o,    32'h0000_0008, "pc_if_o lags pc_fetch by 1 cycle");

        // =====================================================================
        // TC3 — pc_plus4_o = pc_if_o + 4
        // =====================================================================
        $display("\n=== TC3: pc_plus4_o = pc_if_o + 4 ===");
        // Currently pc_if_o = 0x8, so pc_plus4_o should be 0xC
        check32(pc_plus4_o, pc_if_o + 32'd4, "pc_plus4_o = pc_if_o + 4");
        tick;
        check32(pc_plus4_o, pc_if_o + 32'd4, "pc_plus4_o = pc_if_o + 4 (next)");

        // =====================================================================
        // TC4 — Branch taken: pc_src=01
        // =====================================================================
        $display("\n=== TC4: Branch taken (pc_src=2'b01) ===");
        // Record pc_fetch before branch
        @(negedge clk);
        pc_src_i        = 2'b01;
        flush_i         = 1'b1;
        branch_target_i = 32'h0000_0100;   // branch to 0x100

        @(posedge clk); #1;
        // PC should now be 0x100
        check32(pc_fetch_o, 32'h0000_0100, "pc_fetch jumps to branch target 0x100");
        // pc_if should have been flushed to NOP PC
        check32(pc_if_o,    32'h0000_0000, "pc_if_o = bubble PC after flush");

        // Clear branch controls
        @(negedge clk);
        pc_src_i = 2'b00;
        flush_i  = 1'b0;

        // Next tick: sequential from 0x100
        tick; check32(pc_fetch_o, 32'h0000_0104, "sequential from 0x100+4");

        // =====================================================================
        // TC5 — Jump taken: pc_src=10
        // =====================================================================
        $display("\n=== TC5: Jump taken (pc_src=2'b10) ===");
        @(negedge clk);
        pc_src_i      = 2'b10;
        flush_i       = 1'b1;
        jump_target_i = 32'h0000_0200;

        @(posedge clk); #1;
        check32(pc_fetch_o, 32'h0000_0200, "pc_fetch jumps to jump target 0x200");
        check32(pc_if_o,    32'h0000_0000, "pc_if_o = bubble after jump flush");

        @(negedge clk);
        pc_src_i = 2'b00;
        flush_i  = 1'b0;

        tick; check32(pc_fetch_o, 32'h0000_0204, "sequential from 0x200+4");

        // =====================================================================
        // TC6 — Stall: PC and pc_if frozen
        // =====================================================================
        $display("\n=== TC6: Stall freezes PC ===");
        // Let pipeline settle to known state
        repeat(2) tick;
        @(negedge clk);
        begin : stall_test
            reg [31:0] frozen_fetch, frozen_if;
            frozen_fetch = pc_fetch_o;
            frozen_if    = pc_if_o;

            stall_i = 1'b1;
            // Three stall cycles — PC must not move
            tick; check32(pc_fetch_o, frozen_fetch, "pc_fetch frozen cycle 1");
            tick; check32(pc_fetch_o, frozen_fetch, "pc_fetch frozen cycle 2");
            tick; check32(pc_fetch_o, frozen_fetch, "pc_fetch frozen cycle 3");
            check32(pc_if_o, frozen_if, "pc_if_o frozen during stall");

            stall_i = 1'b0;
            tick; check32(pc_fetch_o, frozen_fetch + 32'd4, "pc_fetch resumes after stall");
        end

        // =====================================================================
        // TC7 — Flush overrides stall
        // =====================================================================
        $display("\n=== TC7: Flush overrides stall ===");
        @(negedge clk);
        stall_i         = 1'b1;
        flush_i         = 1'b1;
        pc_src_i        = 2'b01;
        branch_target_i = 32'h0000_0400;

        @(posedge clk); #1;
        check32(pc_fetch_o, 32'h0000_0400, "flush overrides stall: PC=0x400");
        check32(pc_if_o,    32'h0000_0000, "bubble inserted after flush+stall");

        @(negedge clk);
        stall_i  = 1'b0;
        flush_i  = 1'b0;
        pc_src_i = 2'b00;

        // =====================================================================
        // TC8 — pc_fetch and pc_if alignment (one-cycle gap)
        // =====================================================================
        $display("\n=== TC8: pc_fetch and pc_if are one cycle apart ===");
        // Start from clean state
        @(negedge clk); rst_n = 1'b0;
        repeat(2) @(posedge clk);
        @(negedge clk); rst_n = 1'b1;

        begin : align_test
            reg [31:0] fetch0, fetch1, if0, if1;

            @(posedge clk); #1;
            fetch0 = pc_fetch_o;   // should be 0x4 (first cycle after reset)
            if0    = pc_if_o;      // should be 0x0 (one behind)

            tick;
            fetch1 = pc_fetch_o;   // 0x8
            if1    = pc_if_o;      // 0x4 = previous fetch0

            check32(if1, fetch0, "pc_if_o(N+1) == pc_fetch_o(N)");
        end

        // =====================================================================
        // Summary
        // =====================================================================
        $display("\n============================================");
        $display("  Results: %0d PASS   %0d FAIL", pass_count, fail_count);
        $display("============================================\n");
        if (fail_count == 0)
            $display("ALL TESTS PASSED");
        else
            $display("FAILURES DETECTED — review output above");

        $finish;
    end

    initial begin #50000; $display("WATCHDOG TIMEOUT"); $finish; end

endmodule

Project/rtl/tb/results/tb_if_stage.vcd
$date
	Tue May  5 11:21:37 2026
$end
$version
	Icarus Verilog
$end
$timescale
	1ps
$end
$scope module tb_if_stage $end
$var wire 32 ! pc_plus4_o [31:0] $end
$var wire 32 " pc_if_o [31:0] $end
$var wire 32 # pc_fetch_o [31:0] $end
$var parameter 32 $ CLK_PERIOD $end
$var reg 32 % branch_target_i [31:0] $end
$var reg 1 & clk $end
$var reg 1 ' flush_i $end
$var reg 32 ( instr_i [31:0] $end
$var reg 32 ) jump_target_i [31:0] $end
$var reg 2 * pc_src_i [1:0] $end
$var reg 1 + rst_n $end
$var reg 1 , stall_i $end
$var integer 32 - fail_count [31:0] $end
$var integer 32 . pass_count [31:0] $end
$scope module dut $end
$var wire 32 / branch_target_i [31:0] $end
$var wire 1 & clk $end
$var wire 1 ' flush_i $end
$var wire 32 0 instr_i [31:0] $end
$var wire 32 1 jump_target_i [31:0] $end
$var wire 32 2 pc_fetch_o [31:0] $end
$var wire 32 3 pc_if_o [31:0] $end
$var wire 2 4 pc_src_i [1:0] $end
$var wire 1 + rst_n $end
$var wire 1 , stall_i $end
$var wire 32 5 pc_plus4_o [31:0] $end
$var parameter 32 6 PC_NOP $end
$var reg 32 7 next_pc [31:0] $end
$var reg 32 8 pc_if_r [31:0] $end
$var reg 32 9 pc_reg [31:0] $end
$upscope $end
$scope begin align_test $end
$var reg 32 : fetch0 [31:0] $end
$var reg 32 ; fetch1 [31:0] $end
$var reg 32 < if0 [31:0] $end
$var reg 32 = if1 [31:0] $end
$upscope $end
$scope begin stall_test $end
$var reg 32 > frozen_fetch [31:0] $end
$var reg 32 ? frozen_if [31:0] $end
$upscope $end
$scope task check32 $end
$var reg 32 @ expected [31:0] $end
$var reg 32 A got [31:0] $end
$var reg 256 B label [255:0] $end
$upscope $end
$scope task tick $end
$upscope $end
$upscope $end
$enddefinitions $end
$comment Show the parameter values. $end
$dumpall
b0 6
b1010 $
$end
#0
$dumpvars
bx B
bx A
bx @
bx ?
bx >
bx =
bx <
bx ;
bx :
bx 9
bx 8
bx 7
bx 5
b0 4
bx 3
bx 2
b0 1
b10011 0
b0 /
b0 .
b0 -
0,
0+
b0 *
b0 )
b10011 (
0'
0&
b0 %
bx #
bx "
bx !
$end
#5000
b100 7
b0 #
b0 2
b0 9
b100 !
b100 5
b0 "
b0 3
b0 8
1&
#10000
0&
#15000
1&
#16000
b10 .
b11100000110001101011111011010010110011001011111011011110010000000100000001000000010000000111101001000000011000000100000011001000111010101110010011010010110111001100111001000000111001001100101011100110110010101110100 B
b0 @
b0 A
#20000
1+
0&
#25000
b1000 7
b100 #
b100 2
b100 9
1&
#26000
b11 .
b11100000110001101011111011001100110010101110100011000110110100000100000011000010110011001110100011001010111001000100000001100010010000001110100011010010110001101101011001000000011110100100000001100000111100000110100 B
b100 @
b100 A
#30000
0&
#35000
b1100 7
b1000 !
b1000 5
b100 "
b100 3
b100 8
b1000 #
b1000 2
b1000 9
1&
#36000
b100 .
b1110000011000110101111101100110011001010111010001100011011010000010000001100001011001100111010001100101011100100010000000110010001000000111010001101001011000110110101101110011001000000011110100100000001100000111100000111000 B
b1000 @
b1000 A
#40000
0&
#45000
b10000 7
b1100 #
b1100 2
b1100 9
b1100 !
b1100 5
b1000 "
b1000 3
b1000 8
1&
#46000
b111 .
b11100000110001101011111011100000110110001110101011100110011010001011111011011110010000000111101001000000111000001100011010111110110100101100110010111110110111100100000001010110010000000110100 B
b1100 @
b1100 A
#50000
0&
#55000
b10100 7
b10000 !
b10000 5
b1100 "
b1100 3
b1100 8
b10000 #
b10000 2
b10000 9
1&
#56000
b1000 .
b1110000011000110101111101110000011011000111010101110011001101000101111101101111001000000011110100100000011100000110001101011111011010010110011001011111011011110010000000101011001000000011010000100000001010000110111001100101011110000111010000101001 B
b10000 @
b10000 A
#60000
b100000000 7
b100000000 %
b100000000 /
1'
b1 *
b1 4
0&
#65000
b100000000 #
b100000000 2
b100000000 9
b100 !
b100 5
b0 "
b0 3
b0 8
1&
#66000
b1010 .
b1110000011000110101111101101001011001100101111101101111001000000011110100100000011000100111010101100010011000100110110001100101001000000101000001000011001000000110000101100110011101000110010101110010001000000110011001101100011101010111001101101000 B
b0 @
b0 A
#70000
b100000100 7
0'
b0 *
b0 4
0&
#75000
b100001000 7
b100000100 !
b100000100 5
b100000000 "
b100000000 3
b100000000 8
b100000100 #
b100000100 2
b100000100 9
1&
#76000
b1011 .
b111001101100101011100010111010101100101011011100111010001101001011000010110110000100000011001100111001001101111011011010010000000110000011110000011000100110000001100000010101100110100 B
b100000100 @
b100000100 A
#80000
b1000000000 7
b1000000000 )
b1000000000 1
1'
b10 *
b10 4
0&
#85000
b1000000000 #
b1000000000 2
b1000000000 9
b100 !
b100 5
b0 "
b0 3
b0 8
1&
#86000
b1101 .
b110001101011111011010010110011001011111011011110010000000111101001000000110001001110101011000100110001001101100011001010010000001100001011001100111010001100101011100100010000001101010011101010110110101110000001000000110011001101100011101010111001101101000 B
b0 @
b0 A
#90000
b1000000100 7
0'
b0 *
b0 4
0&
#95000
b1000001000 7
b1000000100 !
b1000000100 5
b1000000000 "
b1000000000 3
b1000000000 8
b1000000100 #
b1000000100 2
b1000000100 9
1&
#96000
b1110 .
b111001101100101011100010111010101100101011011100111010001101001011000010110110000100000011001100111001001101111011011010010000000110000011110000011001000110000001100000010101100110100 B
b1000000100 @
b1000000100 A
#100000
0&
#105000
b1000001100 7
b1000001000 #
b1000001000 2
b1000001000 9
b1000001000 !
b1000001000 5
b1000000100 "
b1000000100 3
b1000000100 8
1&
#110000
0&
#115000
b1000010000 7
b1000001100 !
b1000001100 5
b1000001000 "
b1000001000 3
b1000001000 8
b1000001100 #
b1000001100 2
b1000001100 9
1&
#120000
1,
b1000001000 ?
b1000001100 >
0&
#125000
1&
#126000
b1111 .
b111000001100011010111110110011001100101011101000110001101101000001000000110011001110010011011110111101001100101011011100010000001100011011110010110001101101100011001010010000000110001 B
b1000001100 @
b1000001100 A
#130000
0&
#135000
1&
#136000
b10000 .
b111000001100011010111110110011001100101011101000110001101101000001000000110011001110010011011110111101001100101011011100010000001100011011110010110001101101100011001010010000000110010 B
#140000
0&
#145000
1&
#146000
0,
b1000001000 @
b1000001000 A
b10010 .
b11100000110001101011111011010010110011001011111011011110010000001100110011100100110111101111010011001010110111000100000011001000111010101110010011010010110111001100111001000000111001101110100011000010110110001101100 B
#150000
0&
#155000
b1000010100 7
b1000010000 !
b1000010000 5
b1000001100 "
b1000001100 3
b1000001100 8
b1000010000 #
b1000010000 2
b1000010000 9
1&
#156000
b10011 .
b1110000011000110101111101100110011001010111010001100011011010000010000001110010011001010111001101110101011011010110010101110011001000000110000101100110011101000110010101110010001000000111001101110100011000010110110001101100 B
b1000010000 @
b1000010000 A
#160000
b10000000000 7
b10000000000 %
b10000000000 /
b1 *
b1 4
1'
1,
0&
#165000
b10000000000 #
b10000000000 2
b10000000000 9
b100 !
b100 5
b0 "
b0 3
b0 8
1&
#166000
b10101 .
b111010101100010011000100110110001100101001000000110100101101110011100110110010101110010011101000110010101100100001000000110000101100110011101000110010101110010001000000110011001101100011101010111001101101000001010110111001101110100011000010110110001101100 B
b0 @
b0 A
#170000
b10000000100 7
b0 *
b0 4
0'
0,
0&
#175000
b10000001000 7
b10000000100 !
b10000000100 5
b10000000000 "
b10000000000 3
b10000000000 8
b10000000100 #
b10000000100 2
b10000000100 9
1&
#180000
0+
0&
#185000
b100 7
b0 #
b0 2
b0 9
b100 !
b100 5
b0 "
b0 3
b0 8
1&
#190000
0&
#195000
1&
#200000
1+
0&
#205000
b1000 7
b100 #
b100 2
b100 9
1&
#206000
b0 <
b100 :
#210000
0&
#215000
b1100 7
b1000 !
b1000 5
b100 "
b100 3
b100 8
b1000 #
b1000 2
b1000 9
1&
#216000
b10110 .
b111000001100011010111110110100101100110010111110110111100101000010011100010101100110001001010010010000000111101001111010010000001110000011000110101111101100110011001010111010001100011011010000101111101101111001010000100111000101001 B
b100 @
b100 A
b100 =
b1000 ;
