Project/formal/riscv_safety_prove/src/wb_stage.v
//==============================================================================
// wb_stage.v — Write-Back Stage
//------------------------------------------------------------------------------
// Project : ELCT1005 PROJ02 — Pipelined RISC-V CPU with Conv-PE
//
// Responsibilities:
//   1. Select the value to write back to the register file via a 4:1 mux:
//        wb_sel = 2'b00  ->  ALU result    (R-type, I-type, LUI, AUIPC)
//        wb_sel = 2'b01  ->  Load data     (LB, LH, LW, LBU, LHU)
//        wb_sel = 2'b10  ->  Conv-PE result(custom-0)
//        is_jump = 1     ->  PC + 4        (JAL, JALR — overrides wb_sel)
//   2. Drive the register file write port (rd_addr, rd_data, we)
//   3. Expose the write-back value and enable for forwarding to ID stage
//      (riscv_top.v connects wb_data_o / wb_we_o back to id_stage)
//
// Note: is_jump takes priority over wb_sel. JAL and JALR always write
// PC+4 regardless of wb_sel, which is set to 2'b00 in id_stage for those
// instructions (ALU computes the jump target, not the link address).
//==============================================================================
`timescale 1ns / 1ps
`default_nettype none

module wb_stage (
    // From MEM/WB pipeline register
    input  wire [31:0] alu_result_i,
    input  wire [31:0] load_data_i,
    input  wire [31:0] conv_result_i,
    input  wire [31:0] pc_plus4_i,
    input  wire [4:0]  rd_addr_i,
    input  wire [1:0]  wb_sel_i,
    input  wire        reg_write_i,
    input  wire        is_jump_i,

    // Register file write port (to id_stage wb_ inputs)
    output wire [4:0]  wb_addr_o,
    output wire [31:0] wb_data_o,
    output wire        wb_we_o
);

    // =========================================================================
    // 4:1 write-back mux
    // is_jump overrides wb_sel — JAL/JALR always write PC+4
    // =========================================================================
    reg [31:0] wb_data;
    always @* begin
        if (is_jump_i)
            wb_data = pc_plus4_i;          // JAL / JALR link address
        else begin
            case (wb_sel_i)
                2'b00:   wb_data = alu_result_i;   // R-type, I-type, LUI, AUIPC
                2'b01:   wb_data = load_data_i;    // loads
                2'b10:   wb_data = conv_result_i;  // Conv-PE
                default: wb_data = alu_result_i;
            endcase
        end
    end

    // =========================================================================
    // Output assignments
    // =========================================================================
    assign wb_addr_o = rd_addr_i;
    assign wb_data_o = wb_data;
    assign wb_we_o   = reg_write_i;

endmodule

`default_nettype wire

Project/rtl/tb/tb_wb_stage.v
//==============================================================================
// tb_wb_stage.v — Self-Checking Testbench for wb_stage
//------------------------------------------------------------------------------
// Tests:
//   TC1 — wb_sel=00 : ALU result written to rd
//   TC2 — wb_sel=01 : Load data written to rd
//   TC3 — wb_sel=10 : Conv-PE result written to rd
//   TC4 — is_jump=1 : PC+4 written regardless of wb_sel (all 3 values)
//   TC5 — reg_write=0 : wb_we_o deasserted, data still muxed correctly
//   TC6 — rd_addr pass-through : correct address forwarded
//   TC7 — x0 protection : rd_addr=0 passes wb_we=1 (regfile guards x0)
//   TC8 — Boundary values : 0, 0xFFFFFFFF, 0x80000000 through each path
//==============================================================================
`timescale 1ns / 1ps

module tb_wb_stage;

    // ---- DUT ports ----------------------------------------------------------
    reg  [31:0] alu_result_i, load_data_i, conv_result_i, pc_plus4_i;
    reg  [4:0]  rd_addr_i;
    reg  [1:0]  wb_sel_i;
    reg         reg_write_i, is_jump_i;

    wire [4:0]  wb_addr_o;
    wire [31:0] wb_data_o;
    wire        wb_we_o;

    // ---- DUT ----------------------------------------------------------------
    wb_stage dut (
        .alu_result_i  (alu_result_i),
        .load_data_i   (load_data_i),
        .conv_result_i (conv_result_i),
        .pc_plus4_i    (pc_plus4_i),
        .rd_addr_i     (rd_addr_i),
        .wb_sel_i      (wb_sel_i),
        .reg_write_i   (reg_write_i),
        .is_jump_i     (is_jump_i),
        .wb_addr_o     (wb_addr_o),
        .wb_data_o     (wb_data_o),
        .wb_we_o       (wb_we_o)
    );

    // ---- Helpers ------------------------------------------------------------
    integer pass_count, fail_count;

    task chk;
        input [31:0] got, exp;
        input [255:0] lbl;
        begin
            if (got === exp) begin
                $display("  PASS  %-48s  got=0x%08h", lbl, got);
                pass_count = pass_count + 1;
            end else begin
                $display("  FAIL  %-48s  got=0x%08h  exp=0x%08h",
                         lbl, got, exp);
                fail_count = fail_count + 1;
            end
        end
    endtask

    // Apply all inputs, settle 1ns, then check
    task apply;
        input [31:0] alu, ld, conv, pc4;
        input [4:0]  rd;
        input [1:0]  sel;
        input        rw, jmp;
        begin
            alu_result_i  = alu;
            load_data_i   = ld;
            conv_result_i = conv;
            pc_plus4_i    = pc4;
            rd_addr_i     = rd;
            wb_sel_i      = sel;
            reg_write_i   = rw;
            is_jump_i     = jmp;
            #1;
        end
    endtask

    // =========================================================================
    initial begin
        $dumpfile("tb_wb_stage.vcd");
        $dumpvars(0, tb_wb_stage);
        pass_count = 0; fail_count = 0;

        // =====================================================================
        // TC1 — wb_sel=00: ALU result
        // =====================================================================
        $display("\n=== TC1: wb_sel=00 ALU result ===");
        apply(32'hABCD_1234, 32'h1111_1111, 32'h2222_2222, 32'h3333_3333,
              5'd5, 2'b00, 1'b1, 1'b0);
        chk(wb_data_o, 32'hABCD_1234, "wb_data = alu_result");
        chk(wb_we_o,   1,             "wb_we=1");
        chk(wb_addr_o, 5'd5,          "wb_addr=5");

        // =====================================================================
        // TC2 — wb_sel=01: Load data
        // =====================================================================
        $display("\n=== TC2: wb_sel=01 Load data ===");
        apply(32'hABCD_1234, 32'hDEAD_BEEF, 32'h2222_2222, 32'h3333_3333,
              5'd8, 2'b01, 1'b1, 1'b0);
        chk(wb_data_o, 32'hDEAD_BEEF, "wb_data = load_data");
        chk(wb_we_o,   1,             "wb_we=1");

        // =====================================================================
        // TC3 — wb_sel=10: Conv-PE result
        // =====================================================================
        $display("\n=== TC3: wb_sel=10 Conv-PE result ===");
        apply(32'hABCD_1234, 32'hDEAD_BEEF, 32'hCAFE_CAFE, 32'h3333_3333,
              5'd12, 2'b10, 1'b1, 1'b0);
        chk(wb_data_o, 32'hCAFE_CAFE, "wb_data = conv_result");
        chk(wb_we_o,   1,             "wb_we=1");

        // =====================================================================
        // TC4 — is_jump=1: PC+4 overrides all wb_sel values
        // =====================================================================
        $display("\n=== TC4: is_jump=1 overrides wb_sel ===");
        // is_jump overrides wb_sel=00
        apply(32'hAAAA_AAAA, 32'hBBBB_BBBB, 32'hCCCC_CCCC, 32'h0000_0104,
              5'd1, 2'b00, 1'b1, 1'b1);
        chk(wb_data_o, 32'h0000_0104, "is_jump overrides wb_sel=00");

        // is_jump overrides wb_sel=01
        apply(32'hAAAA_AAAA, 32'hBBBB_BBBB, 32'hCCCC_CCCC, 32'h0000_0208,
              5'd1, 2'b01, 1'b1, 1'b1);
        chk(wb_data_o, 32'h0000_0208, "is_jump overrides wb_sel=01");

        // is_jump overrides wb_sel=10
        apply(32'hAAAA_AAAA, 32'hBBBB_BBBB, 32'hCCCC_CCCC, 32'h0000_030C,
              5'd1, 2'b10, 1'b1, 1'b1);
        chk(wb_data_o, 32'h0000_030C, "is_jump overrides wb_sel=10");

        // =====================================================================
        // TC5 — reg_write=0: wb_we_o deasserted
        // =====================================================================
        $display("\n=== TC5: reg_write=0 ===");
        apply(32'hABCD_1234, 32'hDEAD_BEEF, 32'hCAFE_CAFE, 32'h0000_0104,
              5'd9, 2'b00, 1'b0, 1'b0);
        chk(wb_we_o,   0,             "wb_we=0 when reg_write=0");
        chk(wb_data_o, 32'hABCD_1234, "wb_data still muxed (wb_we gates regfile)");

        // reg_write=0 with is_jump
        apply(32'hAAAA_AAAA, 32'hBBBB_BBBB, 32'hCCCC_CCCC, 32'h0000_0104,
              5'd1, 2'b00, 1'b0, 1'b1);
        chk(wb_we_o, 0, "wb_we=0 even with is_jump when reg_write=0");

        // =====================================================================
        // TC6 — rd_addr pass-through
        // =====================================================================
        $display("\n=== TC6: rd_addr pass-through ===");
        apply(32'h0, 32'h0, 32'h0, 32'h0, 5'd31, 2'b00, 1'b1, 1'b0);
        chk(wb_addr_o, 5'd31, "wb_addr=31");

        apply(32'h0, 32'h0, 32'h0, 32'h0, 5'd15, 2'b00, 1'b1, 1'b0);
        chk(wb_addr_o, 5'd15, "wb_addr=15");

        apply(32'h0, 32'h0, 32'h0, 32'h0, 5'd1,  2'b00, 1'b1, 1'b0);
        chk(wb_addr_o, 5'd1,  "wb_addr=1");

        // =====================================================================
        // TC7 — rd_addr=0: wb_we passes through (regfile guards x0)
        // =====================================================================
        $display("\n=== TC7: rd_addr=0 (x0 guard in regfile) ===");
        apply(32'hDEAD_BEEF, 32'h0, 32'h0, 32'h0, 5'd0, 2'b00, 1'b1, 1'b0);
        chk(wb_addr_o, 5'd0,        "wb_addr=0 passed through");
        chk(wb_we_o,   1,           "wb_we=1 (regfile silently ignores x0 write)");
        chk(wb_data_o, 32'hDEAD_BEEF, "wb_data passed (regfile ignores it)");

        // =====================================================================
        // TC8 — Boundary values through each path
        // =====================================================================
        $display("\n=== TC8: Boundary values ===");
        // Zero through ALU path
        apply(32'h0, 32'hFFFF_FFFF, 32'hFFFF_FFFF, 32'hFFFF_FFFF,
              5'd5, 2'b00, 1'b1, 1'b0);
        chk(wb_data_o, 32'h0, "ALU path: zero");

        // 0xFFFFFFFF through load path
        apply(32'h0, 32'hFFFF_FFFF, 32'h0, 32'h0,
              5'd5, 2'b01, 1'b1, 1'b0);
        chk(wb_data_o, 32'hFFFF_FFFF, "Load path: 0xFFFFFFFF");

        // 0x80000000 through conv path
        apply(32'h0, 32'h0, 32'h8000_0000, 32'h0,
              5'd5, 2'b10, 1'b1, 1'b0);
        chk(wb_data_o, 32'h8000_0000, "Conv path: 0x80000000");

        // 0xFFFFFFFF through jump path
        apply(32'h0, 32'h0, 32'h0, 32'hFFFF_FFFC,
              5'd5, 2'b00, 1'b1, 1'b1);
        chk(wb_data_o, 32'hFFFF_FFFC, "Jump path: 0xFFFFFFFC");

        // =====================================================================
        // Summary
        // =====================================================================
        $display("\n============================================");
        $display("  Results: %0d PASS   %0d FAIL", pass_count, fail_count);
        $display("============================================\n");
        if (fail_count == 0)
            $display("ALL TESTS PASSED");
        else
            $display("FAILURES DETECTED");

        $finish;
    end

endmodule

Project/rtl/tb/results/tb_wb_stage.vcd
$date
	Tue May  5 12:18:47 2026
$end
$version
	Icarus Verilog
$end
$timescale
	1ps
$end
$scope module tb_wb_stage $end
$var wire 1 ! wb_we_o $end
$var wire 32 " wb_data_o [31:0] $end
$var wire 5 # wb_addr_o [4:0] $end
$var reg 32 $ alu_result_i [31:0] $end
$var reg 32 % conv_result_i [31:0] $end
$var reg 1 & is_jump_i $end
$var reg 32 ' load_data_i [31:0] $end
$var reg 32 ( pc_plus4_i [31:0] $end
$var reg 5 ) rd_addr_i [4:0] $end
$var reg 1 * reg_write_i $end
$var reg 2 + wb_sel_i [1:0] $end
$var integer 32 , fail_count [31:0] $end
$var integer 32 - pass_count [31:0] $end
$scope module dut $end
$var wire 32 . alu_result_i [31:0] $end
$var wire 32 / conv_result_i [31:0] $end
$var wire 1 & is_jump_i $end
$var wire 32 0 load_data_i [31:0] $end
$var wire 32 1 pc_plus4_i [31:0] $end
$var wire 5 2 rd_addr_i [4:0] $end
$var wire 1 * reg_write_i $end
$var wire 5 3 wb_addr_o [4:0] $end
$var wire 32 4 wb_data_o [31:0] $end
$var wire 2 5 wb_sel_i [1:0] $end
$var wire 1 ! wb_we_o $end
$var reg 32 6 wb_data [31:0] $end
$upscope $end
$scope task apply $end
$var reg 32 7 alu [31:0] $end
$var reg 32 8 conv [31:0] $end
$var reg 1 9 jmp $end
$var reg 32 : ld [31:0] $end
$var reg 32 ; pc4 [31:0] $end
$var reg 5 < rd [4:0] $end
$var reg 1 = rw $end
$var reg 2 > sel [1:0] $end
$upscope $end
$scope task chk $end
$var reg 32 ? exp [31:0] $end
$var reg 32 @ got [31:0] $end
$var reg 256 A lbl [255:0] $end
$upscope $end
$upscope $end
$enddefinitions $end
$comment Show the parameter values. $end
$dumpall
$end
#0
$dumpvars
bx A
bx @
bx ?
b0 >
1=
b101 <
b110011001100110011001100110011 ;
b10001000100010001000100010001 :
09
b100010001000100010001000100010 8
b10101011110011010001001000110100 7
b10101011110011010001001000110100 6
b0 5
b10101011110011010001001000110100 4
b101 3
b101 2
b110011001100110011001100110011 1
b10001000100010001000100010001 0
b100010001000100010001000100010 /
b10101011110011010001001000110100 .
b0 -
b0 ,
b0 +
1*
b101 )
b110011001100110011001100110011 (
b10001000100010001000100010001 '
0&
b100010001000100010001000100010 %
b10101011110011010001001000110100 $
b101 #
b10101011110011010001001000110100 "
1!
$end
#1000
b11011110101011011011111011101111 "
b11011110101011011011111011101111 4
b11011110101011011011111011101111 6
b1 +
b1 5
b1000 #
b1000 3
b1000 )
b1000 2
b11011110101011011011111011101111 '
b11011110101011011011111011101111 0
b1 >
b1000 <
b11011110101011011011111011101111 :
b11 -
b11101110110001001011111011000010110010001100100011100100011110100110101 A
b101 ?
b101 @
#2000
b11001010111111101100101011111110 "
b11001010111111101100101011111110 4
b11001010111111101100101011111110 6
b10 +
b10 5
b1100 #
b1100 3
b1100 )
b1100 2
b11001010111111101100101011111110 %
b11001010111111101100101011111110 /
b10 >
b1100 <
b11001010111111101100101011111110 8
b101 -
b1110111011000100101111101110111011001010011110100110001 A
b1 ?
b1 @
#3000
b100000100 "
b100000100 4
b100000100 6
1&
b0 +
b0 5
b1 #
b1 3
b1 )
b1 2
b100000100 (
b100000100 1
b11001100110011001100110011001100 %
b11001100110011001100110011001100 /
b10111011101110111011101110111011 '
b10111011101110111011101110111011 0
b10101010101010101010101010101010 $
b10101010101010101010101010101010 .
19
b0 >
b1 <
b100000100 ;
b11001100110011001100110011001100 8
b10111011101110111011101110111011 :
b10101010101010101010101010101010 7
b111 -
b1110111011000100101111101110111011001010011110100110001 A
b1 ?
b1 @
#4000
b1000001000 "
b1000001000 4
b1000001000 6
b1 +
b1 5
b1000001000 (
b1000001000 1
b1 >
b1000001000 ;
b1000 -
b11010010111001101011111011010100111010101101101011100000010000001101111011101100110010101110010011100100110100101100100011001010111001100100000011101110110001001011111011100110110010101101100001111010011000000110000 A
b100000100 ?
b100000100 @
#5000
b1100001100 "
b1100001100 4
b1100001100 6
b10 +
b10 5
b1100001100 (
b1100001100 1
b10 >
b1100001100 ;
b1001 -
b11010010111001101011111011010100111010101101101011100000010000001101111011101100110010101110010011100100110100101100100011001010111001100100000011101110110001001011111011100110110010101101100001111010011000000110001 A
b1000001000 ?
b1000001000 @
#6000
b10101011110011010001001000110100 "
b10101011110011010001001000110100 4
b10101011110011010001001000110100 6
0&
0!
0*
b0 +
b0 5
b1001 #
b1001 3
b1001 )
b1001 2
b100000100 (
b100000100 1
b11001010111111101100101011111110 %
b11001010111111101100101011111110 /
b11011110101011011011111011101111 '
b11011110101011011011111011101111 0
b10101011110011010001001000110100 $
b10101011110011010001001000110100 .
09
0=
b0 >
b1001 <
b100000100 ;
b11001010111111101100101011111110 8
b11011110101011011011111011101111 :
b10101011110011010001001000110100 7
b1010 -
b11010010111001101011111011010100111010101101101011100000010000001101111011101100110010101110010011100100110100101100100011001010111001100100000011101110110001001011111011100110110010101101100001111010011000100110000 A
b1100001100 ?
b1100001100 @
#7000
b100000100 "
b100000100 4
b100000100 6
1&
b1 #
b1 3
b1 )
b1 2
b11001100110011001100110011001100 %
b11001100110011001100110011001100 /
b10111011101110111011101110111011 '
b10111011101110111011101110111011 0
b10101010101010101010101010101010 $
b10101010101010101010101010101010 .
19
b1 <
b11001100110011001100110011001100 8
b10111011101110111011101110111011 :
b10101010101010101010101010101010 7
b1100 -
b111010001101001011011000110110000100000011011010111010101111000011001010110010000100000001010000111011101100010010111110111011101100101001000000110011101100001011101000110010101110011001000000111001001100101011001110110011001101001011011000110010100101001 A
b10101011110011010001001000110100 ?
b10101011110011010001001000110100 @
#8000
b0 "
b0 4
b0 6
0&
1!
1*
b11111 #
b11111 3
b11111 )
b11111 2
b0 (
b0 1
b0 %
b0 /
b0 '
b0 0
b0 $
b0 .
09
1=
b11111 <
b0 ;
b0 8
b0 :
b0 7
b1101 -
b110010101101110001000000111011101101001011101000110100000100000011010010111001101011111011010100111010101101101011100000010000001110111011010000110010101101110001000000111001001100101011001110101111101110111011100100110100101110100011001010011110100110000 A
b0 ?
b0 @
#9000
b1111 #
b1111 3
b1111 )
b1111 2
b1111 <
b1110 -
b1110111011000100101111101100001011001000110010001110010001111010011001100110001 A
b11111 ?
b11111 @
#10000
b1 #
b1 3
b1 )
b1 2
b1 <
b1111 -
b1110111011000100101111101100001011001000110010001110010001111010011000100110101 A
b1111 ?
b1111 @
#11000
b11011110101011011011111011101111 "
b11011110101011011011111011101111 4
b11011110101011011011111011101111 6
b0 #
b0 3
b0 )
b0 2
b11011110101011011011111011101111 $
b11011110101011011011111011101111 .
b0 <
b11011110101011011011111011101111 7
b10000 -
b11101110110001001011111011000010110010001100100011100100011110100110001 A
b1 ?
b1 @
#12000
b0 "
b0 4
b0 6
b101 #
b101 3
b101 )
b101 2
b11111111111111111111111111111111 (
b11111111111111111111111111111111 1
b11111111111111111111111111111111 %
b11111111111111111111111111111111 /
b11111111111111111111111111111111 '
b11111111111111111111111111111111 0
b0 $
b0 .
b101 <
b11111111111111111111111111111111 ;
b11111111111111111111111111111111 8
b11111111111111111111111111111111 :
b0 7
b10011 -
b110010001100001011101000110000100100000011100000110000101110011011100110110010101100100001000000010100001110010011001010110011101100110011010010110110001100101001000000110100101100111011011100110111101110010011001010111001100100000011010010111010000101001 A
b11011110101011011011111011101111 ?
b11011110101011011011111011101111 @
#13000
b11111111111111111111111111111111 "
b11111111111111111111111111111111 4
b11111111111111111111111111111111 6
b1 +
b1 5
b0 (
b0 1
b0 %
b0 /
b1 >
b0 ;
b0 8
b10100 -
b100000101001100010101010010000001110000011000010111010001101000001110100010000001111010011001010111001001101111 A
b0 ?
b0 @
#14000
b10000000000000000000000000000000 "
b10000000000000000000000000000000 4
b10000000000000000000000000000000 6
b10 +
b10 5
b10000000000000000000000000000000 %
b10000000000000000000000000000000 /
b0 '
b0 0
b10 >
b10000000000000000000000000000000 8
b0 :
b10101 -
b10011000110111101100001011001000010000001110000011000010111010001101000001110100010000000110000011110000100011001000110010001100100011001000110010001100100011001000110 A
b11111111111111111111111111111111 ?
b11111111111111111111111111111111 @
#15000
b11111111111111111111111111111100 "
b11111111111111111111111111111100 4
b11111111111111111111111111111100 6
1&
b0 +
b0 5
b11111111111111111111111111111100 (
b11111111111111111111111111111100 1
b0 %
b0 /
19
b0 >
b11111111111111111111111111111100 ;
b0 8
b10110 -
b10000110110111101101110011101100010000001110000011000010111010001101000001110100010000000110000011110000011100000110000001100000011000000110000001100000011000000110000 A
b10000000000000000000000000000000 ?
b10000000000000000000000000000000 @
#16000
b10111 -
b10010100111010101101101011100000010000001110000011000010111010001101000001110100010000000110000011110000100011001000110010001100100011001000110010001100100011001000011 A
b11111111111111111111111111111100 ?
b11111111111111111111111111111100 @
