Project/formal/riscv_safety_prove/src/regfile.v
//==============================================================================
// regfile.v — RV32I Integer Register File
//------------------------------------------------------------------------------
// Project : ELCT1005 PROJ02 — Pipelined RISC-V CPU with Conv-PE
// Spec    : 32 general-purpose registers (x0–x31), each 32 bits wide.
//           x0 is hardwired to zero — reads always return 0, writes silently
//           ignored. Total architectural state: 31 × 32 = 992 bits.
//
// Ports:
//   Read port A (async/combinational — ID stage):
//     rs1_addr[4:0]  -> rs1_data[31:0]
//   Read port B (async/combinational — ID stage):
//     rs2_addr[4:0]  -> rs2_data[31:0]
//   Write port (synchronous, rising edge — WB stage):
//     clk, rst_n, we, rd_addr[4:0], rd_data[31:0]
//
// Implementation:
//   FF array with two combinational read muxes. NO memory primitive
//   ($readmemh / synchronous-read RAM) — must synthesise to standard-cell
//   flip-flops so all 992 state bits appear on the scan chain (Phase 4 DFT).
//
// Formal properties (Phase 1):
//   X0_SAFE — write-enable to x0 with non-zero data must never occur.
//             Enforced both by the write guard below AND the Phase 1 SBY
//             property in riscv_props.v.
//==============================================================================
`timescale 1ns / 1ps
`default_nettype none

module regfile (
    input  wire        clk,
    input  wire        rst_n,       // active-low synchronous reset

    // Read port A (combinational)
    input  wire [4:0]  rs1_addr,
    output wire [31:0] rs1_data,

    // Read port B (combinational)
    input  wire [4:0]  rs2_addr,
    output wire [31:0] rs2_data,

    // Write port (synchronous)
    input  wire        we,
    input  wire [4:0]  rd_addr,
    input  wire [31:0] rd_data
);

    // -------------------------------------------------------------------------
    // Storage — 32 × 32-bit flip-flop array.
    // regs[0] is never written (x0 guard below) and reads return 0 via the
    // combinational mux, so its power-up value is irrelevant. Keeping it in
    // the array avoids width-mismatch complexity; Yosys will optimise it away.
    // -------------------------------------------------------------------------
    reg [31:0] regs [1:31];  // x1–x31 only; x0 handled separately

    // -------------------------------------------------------------------------
    // Synchronous write with synchronous reset.
    //   - rst_n = 0  → clear every register to 0 on the next rising edge.
    //   - we = 1 AND rd_addr != 0 → write rd_data to regs[rd_addr].
    //   - Writes to rd_addr == 0 are silently ignored (X0_SAFE guarantee).
    // -------------------------------------------------------------------------
    integer idx;
    always @(posedge clk) begin
        if (!rst_n) begin
            for (idx = 1; idx <= 31; idx = idx + 1)
                regs[idx] <= 32'h00000000;
        end else if (we && (rd_addr != 5'd0)) begin
            regs[rd_addr] <= rd_data;
        end
    end

    // -------------------------------------------------------------------------
    // Asynchronous combinational reads.
    //   x0 always returns 0 regardless of the array content.
    //   x1–x31 return the current FF value directly (no clock edge needed).
    // -------------------------------------------------------------------------
    assign rs1_data = (rs1_addr == 5'd0) ? 32'h00000000 : regs[rs1_addr];
    assign rs2_data = (rs2_addr == 5'd0) ? 32'h00000000 : regs[rs2_addr];

endmodule

`default_nettype wire

Project/rtl/tb/tb_regfile.v
//==============================================================================
// tb_regfile.v — Self-Checking Directed Testbench for regfile
//------------------------------------------------------------------------------
// Tests:
//   TC1 — Reset: all registers read 0 after rst_n de-asserted
//   TC2 — x0 hardwired to 0: write non-zero to x0, read back must be 0
//   TC3 — Basic write / read: write unique value to every register x1–x31
//   TC4 — Both read ports simultaneously: rs1 and rs2 read different regs
//   TC5 — Write enable gate: we=0 must not change register contents
//   TC6 — Async read same cycle as write: read port sees OLD value
//          (write is synchronous — new value visible one cycle later)
//   TC7 — Synchronous reset clears all: write to several regs, assert
//          rst_n=0 for one cycle, all registers must return to 0
//   TC8 — Write port priority: two consecutive writes to the same register,
//          second write wins
//==============================================================================
`timescale 1ns / 1ps

module tb_regfile;

    localparam CLK_PERIOD = 10;

    // ---- DUT ports ----------------------------------------------------------
    reg        clk, rst_n, we;
    reg  [4:0] rs1_addr, rs2_addr, rd_addr;
    reg  [31:0] rd_data;
    wire [31:0] rs1_data, rs2_data;

    // ---- DUT ----------------------------------------------------------------
    regfile dut (
        .clk      (clk),
        .rst_n    (rst_n),
        .rs1_addr (rs1_addr),
        .rs2_addr (rs2_addr),
        .rs1_data (rs1_data),
        .rs2_data (rs2_data),
        .we       (we),
        .rd_addr  (rd_addr),
        .rd_data  (rd_data)
    );

    // ---- Clock --------------------------------------------------------------
    initial clk = 0;
    always #(CLK_PERIOD/2) clk = ~clk;

    // ---- Helpers ------------------------------------------------------------
    integer pass_count, fail_count;

    task check;
        input [31:0] got;
        input [31:0] expected;
        input [255:0] label;
        begin
            if (got === expected) begin
                $display("  PASS  %-45s  got=0x%08h", label, got);
                pass_count = pass_count + 1;
            end else begin
                $display("  FAIL  %-45s  got=0x%08h  exp=0x%08h",
                         label, got, expected);
                fail_count = fail_count + 1;
            end
        end
    endtask

    // Write one register and wait one cycle for the write to land
    task write_reg;
        input [4:0]  addr;
        input [31:0] data;
        begin
            @(negedge clk);
            we      = 1'b1;
            rd_addr = addr;
            rd_data = data;
            @(negedge clk);
            we      = 1'b0;
            rd_addr = 5'd0;
            rd_data = 32'h0;
        end
    endtask

    // Read register via rs1 port (combinational — valid immediately)
    task read_rs1;
        input  [4:0]  addr;
        output [31:0] data;
        begin
            rs1_addr = addr;
            #1;                 // tiny delta so combinational output settles
            data = rs1_data;
        end
    endtask

    // Read register via rs2 port
    task read_rs2;
        input  [4:0]  addr;
        output [31:0] data;
        begin
            rs2_addr = addr;
            #1;
            data = rs2_data;
        end
    endtask

    // =========================================================================
    integer i;
    reg [31:0] r1, r2;

    initial begin
        $dumpfile("tb_regfile.vcd");
        $dumpvars(0, tb_regfile);

        pass_count = 0;
        fail_count = 0;

        // Default inputs
        rst_n    = 1'b0;
        we       = 1'b0;
        rs1_addr = 5'd0;
        rs2_addr = 5'd0;
        rd_addr  = 5'd0;
        rd_data  = 32'h0;

        // =====================================================================
        // TC1 — Reset: every register reads 0
        // =====================================================================
        $display("\n=== TC1: Reset — all registers read 0 ===");
        repeat(3) @(posedge clk);
        for (i = 0; i < 32; i = i + 1) begin
            read_rs1(i[4:0], r1);
            check(r1, 32'h0, "xi = 0 during reset");
        end

        // Release reset
        @(negedge clk);
        rst_n = 1'b1;
        @(negedge clk);

        // =====================================================================
        // TC2 — x0 is hardwired to 0
        // =====================================================================
        $display("\n=== TC2: x0 hardwired to 0 ===");
        // Attempt write to x0
        @(negedge clk);
        we = 1'b1; rd_addr = 5'd0; rd_data = 32'hDEADBEEF;
        @(negedge clk);
        we = 1'b0;

        read_rs1(5'd0, r1);
        check(r1, 32'h0, "x0 rs1 = 0 after write attempt");
        read_rs2(5'd0, r2);
        check(r2, 32'h0, "x0 rs2 = 0 after write attempt");

        // =====================================================================
        // TC3 — Write unique value to every register x1–x31, then read back
        // =====================================================================
        $display("\n=== TC3: Write/read all registers x1–x31 ===");
        for (i = 1; i <= 31; i = i + 1)
            write_reg(i[4:0], 32'hA0000000 | i);   // unique pattern per reg

        for (i = 1; i <= 31; i = i + 1) begin
            read_rs1(i[4:0], r1);
            check(r1, 32'hA0000000 | i, "xi write/read via rs1");
        end

        // =====================================================================
        // TC4 — Both read ports simultaneously, different registers
        // =====================================================================
        $display("\n=== TC4: Dual read port — rs1 and rs2 simultaneously ===");
        // x5 = 0xAAAAAAAA, x17 = 0xBBBBBBBB
        write_reg(5'd5,  32'hAAAAAAAA);
        write_reg(5'd17, 32'hBBBBBBBB);

        rs1_addr = 5'd5;
        rs2_addr = 5'd17;
        #1;
        check(rs1_data, 32'hAAAAAAAA, "rs1 port reads x5 = 0xAAAAAAAA");
        check(rs2_data, 32'hBBBBBBBB, "rs2 port reads x17 = 0xBBBBBBBB");

        // Swap addresses
        rs1_addr = 5'd17;
        rs2_addr = 5'd5;
        #1;
        check(rs1_data, 32'hBBBBBBBB, "rs1 port reads x17 = 0xBBBBBBBB");
        check(rs2_data, 32'hAAAAAAAA, "rs2 port reads x5 = 0xAAAAAAAA");

        // =====================================================================
        // TC5 — Write enable gate: we=0 must not change register
        // =====================================================================
        $display("\n=== TC5: we=0 does not write ===");
        write_reg(5'd10, 32'h12345678);     // establish known value

        @(negedge clk);
        we = 1'b0; rd_addr = 5'd10; rd_data = 32'hDEADBEEF;  // we=0
        @(negedge clk);
        we = 1'b0;

        read_rs1(5'd10, r1);
        check(r1, 32'h12345678, "x10 unchanged when we=0");

        // =====================================================================
        // TC6 — Async read sees OLD value in same cycle as write
        // =====================================================================
        $display("\n=== TC6: Async read sees old value same cycle as write ===");
        write_reg(5'd7, 32'hCAFECAFE);      // known value in x7

        @(negedge clk);
        // Start write of new value — read port checked BEFORE rising edge lands
        we = 1'b1; rd_addr = 5'd7; rd_data = 32'h11111111;
        rs1_addr = 5'd7;
        #1;  // combinational settle — write hasn't clocked in yet
        check(rs1_data, 32'hCAFECAFE, "rs1 sees OLD value same cycle as write");

        // After the rising edge the new value should be visible
        @(negedge clk);
        we = 1'b0;
        read_rs1(5'd7, r1);
        check(r1, 32'h11111111, "rs1 sees NEW value one cycle after write");

        // =====================================================================
        // TC7 — Synchronous reset clears all registers
        // =====================================================================
        $display("\n=== TC7: Synchronous reset clears all registers ===");
        // Write non-zero to several registers
        write_reg(5'd1,  32'hFFFFFFFF);
        write_reg(5'd15, 32'h55555555);
        write_reg(5'd31, 32'h12345678);

        // Assert reset for one cycle
        @(negedge clk);
        rst_n = 1'b0;
        @(negedge clk);
        rst_n = 1'b1;
        @(negedge clk);

        for (i = 1; i <= 31; i = i + 1) begin
            read_rs1(i[4:0], r1);
            check(r1, 32'h0, "xi = 0 after reset");
        end

        // =====================================================================
        // TC8 — Two consecutive writes to the same register, second wins
        // =====================================================================
        $display("\n=== TC8: Two consecutive writes — second wins ===");
        write_reg(5'd20, 32'h11111111);
        write_reg(5'd20, 32'h22222222);

        read_rs1(5'd20, r1);
        check(r1, 32'h22222222, "x20 = second write value 0x22222222");

        // =====================================================================
        // Summary
        // =====================================================================
        $display("\n============================================");
        $display("  Results: %0d PASS   %0d FAIL", pass_count, fail_count);
        $display("============================================\n");
        if (fail_count == 0)
            $display("ALL TESTS PASSED");
        else
            $display("FAILURES DETECTED — review output above");

        $finish;
    end

    initial begin
        #(CLK_PERIOD * 5000);
        $display("WATCHDOG TIMEOUT");
        $finish;
    end

endmodule

Project/tb_regfile.vcd
$date
	Tue May  5 10:50:46 2026
$end
$version
	Icarus Verilog
$end
$timescale
	1ps
$end
$scope module tb_regfile $end
$var wire 32 ! rs2_data [31:0] $end
$var wire 32 " rs1_data [31:0] $end
$var parameter 32 # CLK_PERIOD $end
$var reg 1 $ clk $end
$var reg 32 % r1 [31:0] $end
$var reg 32 & r2 [31:0] $end
$var reg 5 ' rd_addr [4:0] $end
$var reg 32 ( rd_data [31:0] $end
$var reg 5 ) rs1_addr [4:0] $end
$var reg 5 * rs2_addr [4:0] $end
$var reg 1 + rst_n $end
$var reg 1 , we $end
$var integer 32 - fail_count [31:0] $end
$var integer 32 . i [31:0] $end
$var integer 32 / pass_count [31:0] $end
$scope module dut $end
$var wire 1 $ clk $end
$var wire 5 0 rd_addr [4:0] $end
$var wire 32 1 rd_data [31:0] $end
$var wire 5 2 rs1_addr [4:0] $end
$var wire 5 3 rs2_addr [4:0] $end
$var wire 1 + rst_n $end
$var wire 1 , we $end
$var wire 32 4 rs2_data [31:0] $end
$var wire 32 5 rs1_data [31:0] $end
$var integer 32 6 idx [31:0] $end
$upscope $end
$scope task check $end
$var reg 32 7 expected [31:0] $end
$var reg 32 8 got [31:0] $end
$var reg 256 9 label [255:0] $end
$upscope $end
$scope task read_rs1 $end
$var reg 5 : addr [4:0] $end
$var reg 32 ; data [31:0] $end
$upscope $end
$scope task read_rs2 $end
$var reg 5 < addr [4:0] $end
$var reg 32 = data [31:0] $end
$upscope $end
$scope task write_reg $end
$var reg 5 > addr [4:0] $end
$var reg 32 ? data [31:0] $end
$upscope $end
$upscope $end
$enddefinitions $end
$comment Show the parameter values. $end
$dumpall
b1010 #
$end
#0
$dumpvars
bx ?
bx >
bx =
bx <
bx ;
bx :
bx 9
bx 8
bx 7
bx 6
b0 5
b0 4
b0 3
b0 2
b0 1
b0 0
b0 /
bx .
b0 -
0,
0+
b0 *
b0 )
b0 (
b0 '
bx &
bx %
0$
b0 "
b0 !
$end
#5000
b100000 6
1$
#10000
0$
#15000
b100000 6
1$
#20000
0$
#25000
b100000 6
b0 :
b0 .
1$
#26000
b1 )
b1 2
b1 :
b1 .
b1 /
b1111000011010010010000000111101001000000011000000100000011001000111010101110010011010010110111001100111001000000111001001100101011100110110010101110100 9
b0 7
b0 8
b0 %
b0 ;
#27000
b10 )
b10 2
b10 :
b10 .
b10 /
#28000
b11 )
b11 2
b11 :
b11 .
b11 /
#29000
b100 )
b100 2
b100 :
b100 .
b100 /
#30000
b101 )
b101 2
b101 :
b101 .
b101 /
0$
#31000
b110 )
b110 2
b110 :
b110 .
b110 /
#32000
b111 )
b111 2
b111 :
b111 .
b111 /
#33000
b1000 )
b1000 2
b1000 :
b1000 .
b1000 /
#34000
b1001 )
b1001 2
b1001 :
b1001 .
b1001 /
#35000
b100000 6
b1010 )
b1010 2
b1010 :
b1010 .
b1010 /
1$
#36000
b1011 )
b1011 2
b1011 :
b1011 .
b1011 /
#37000
b1100 )
b1100 2
b1100 :
b1100 .
b1100 /
#38000
b1101 )
b1101 2
b1101 :
b1101 .
b1101 /
#39000
b1110 )
b1110 2
b1110 :
b1110 .
b1110 /
#40000
b1111 )
b1111 2
b1111 :
b1111 .
b1111 /
0$
#41000
b10000 )
b10000 2
b10000 :
b10000 .
b10000 /
#42000
b10001 )
b10001 2
b10001 :
b10001 .
b10001 /
#43000
b10010 )
b10010 2
b10010 :
b10010 .
b10010 /
#44000
b10011 )
b10011 2
b10011 :
b10011 .
b10011 /
#45000
b100000 6
b10100 )
b10100 2
b10100 :
b10100 .
b10100 /
1$
#46000
b10101 )
b10101 2
b10101 :
b10101 .
b10101 /
#47000
b10110 )
b10110 2
b10110 :
b10110 .
b10110 /
#48000
b10111 )
b10111 2
b10111 :
b10111 .
b10111 /
#49000
b11000 )
b11000 2
b11000 :
b11000 .
b11000 /
#50000
b11001 )
b11001 2
b11001 :
b11001 .
b11001 /
0$
#51000
b11010 )
b11010 2
b11010 :
b11010 .
b11010 /
#52000
b11011 )
b11011 2
b11011 :
b11011 .
b11011 /
#53000
b11100 )
b11100 2
b11100 :
b11100 .
b11100 /
#54000
b11101 )
b11101 2
b11101 :
b11101 .
b11101 /
#55000
b100000 6
b11110 )
b11110 2
b11110 :
b11110 .
b11110 /
1$
#56000
b11111 )
b11111 2
b11111 :
b11111 .
b11111 /
#57000
b100000 .
b100000 /
#60000
1+
0$
#65000
1$
#70000
0$
#75000
1$
#80000
b11011110101011011011111011101111 (
b11011110101011011011111011101111 1
1,
0$
#85000
1$
#90000
b0 )
b0 2
b0 :
0,
0$
#91000
b0 <
b100001 /
b11110000011000000100000011100100111001100110001001000000011110100100000001100000010000001100001011001100111010001100101011100100010000001110111011100100110100101110100011001010010000001100001011101000111010001100101011011010111000001110100 9
#92000
b10100000000000000000000000000001 ?
b1 >
b1 .
b100010 /
b11110000011000000100000011100100111001100110010001000000011110100100000001100000010000001100001011001100111010001100101011100100010000001110111011100100110100101110100011001010010000001100001011101000111010001100101011011010111000001110100 9
b0 &
b0 =
#95000
1$
#100000
b10100000000000000000000000000001 (
b10100000000000000000000000000001 1
b1 '
b1 0
1,
0$
#105000
1$
#110000
b10100000000000000000000000000010 ?
b10 >
b10 .
b0 (
b0 1
b0 '
b0 0
0,
0$
#115000
1$
#120000
b10100000000000000000000000000010 (
b10100000000000000000000000000010 1
b10 '
b10 0
1,
0$
#125000
1$
#130000
b10100000000000000000000000000011 ?
b11 >
b11 .
b0 (
b0 1
b0 '
b0 0
0,
0$
#135000
1$
#140000
b10100000000000000000000000000011 (
b10100000000000000000000000000011 1
b11 '
b11 0
1,
0$
#145000
1$
#150000
b10100000000000000000000000000100 ?
b100 >
b100 .
b0 (
b0 1
b0 '
b0 0
0,
0$
#155000
1$
#160000
b10100000000000000000000000000100 (
b10100000000000000000000000000100 1
b100 '
b100 0
1,
0$
#165000
1$
#170000
b10100000000000000000000000000101 ?
b101 >
b101 .
b0 (
b0 1
b0 '
b0 0
0,
0$
#175000
1$
#180000
b10100000000000000000000000000101 (
b10100000000000000000000000000101 1
b101 '
b101 0
1,
0$
#185000
1$
#190000
b10100000000000000000000000000110 ?
b110 >
b110 .
b0 (
b0 1
b0 '
b0 0
0,
0$
#195000
1$
#200000
b10100000000000000000000000000110 (
b10100000000000000000000000000110 1
b110 '
b110 0
1,
0$
#205000
1$
#210000
b10100000000000000000000000000111 ?
b111 >
b111 .
b0 (
b0 1
b0 '
b0 0
0,
0$
#215000
1$
#220000
b10100000000000000000000000000111 (
b10100000000000000000000000000111 1
b111 '
b111 0
1,
0$
#225000
1$
#230000
b10100000000000000000000000001000 ?
b1000 >
b1000 .
b0 (
b0 1
b0 '
b0 0
0,
0$
#235000
1$
#240000
b10100000000000000000000000001000 (
b10100000000000000000000000001000 1
b1000 '
b1000 0
1,
0$
#245000
1$
#250000
b10100000000000000000000000001001 ?
b1001 >
b1001 .
b0 (
b0 1
b0 '
b0 0
0,
0$
#255000
1$
#260000
b10100000000000000000000000001001 (
b10100000000000000000000000001001 1
b1001 '
b1001 0
1,
0$
#265000
1$
#270000
b10100000000000000000000000001010 ?
b1010 >
b1010 .
b0 (
b0 1
b0 '
b0 0
0,
0$
#275000
1$
#280000
b10100000000000000000000000001010 (
b10100000000000000000000000001010 1
b1010 '
b1010 0
1,
0$
#285000
1$
#290000
b10100000000000000000000000001011 ?
b1011 >
b1011 .
b0 (
b0 1
b0 '
b0 0
0,
0$
#295000
1$
#300000
b10100000000000000000000000001011 (
b10100000000000000000000000001011 1
b1011 '
b1011 0
1,
0$
#305000
1$
#310000
b10100000000000000000000000001100 ?
b1100 >
b1100 .
b0 (
b0 1
b0 '
b0 0
0,
0$
#315000
1$
#320000
b10100000000000000000000000001100 (
b10100000000000000000000000001100 1
b1100 '
b1100 0
1,
0$
#325000
1$
#330000
b10100000000000000000000000001101 ?
b1101 >
b1101 .
b0 (
b0 1
b0 '
b0 0
0,
0$
#335000
1$
#340000
b10100000000000000000000000001101 (
b10100000000000000000000000001101 1
b1101 '
b1101 0
1,
0$
#345000
1$
#350000
b10100000000000000000000000001110 ?
b1110 >
b1110 .
b0 (
b0 1
b0 '
b0 0
0,
0$
#355000
1$
#360000
b10100000000000000000000000001110 (
b10100000000000000000000000001110 1
b1110 '
b1110 0
1,
0$
#365000
1$
#370000
b10100000000000000000000000001111 ?
b1111 >
b1111 .
b0 (
b0 1
b0 '
b0 0
0,
0$
#375000
1$
#380000
b10100000000000000000000000001111 (
b10100000000000000000000000001111 1
b1111 '
b1111 0
1,
0$
#385000
1$
#390000
b10100000000000000000000000010000 ?
b10000 >
b10000 .
b0 (
b0 1
b0 '
b0 0
0,
0$
#395000
1$
#400000
b10100000000000000000000000010000 (
b10100000000000000000000000010000 1
b10000 '
b10000 0
1,
0$
#405000
1$
#410000
b10100000000000000000000000010001 ?
b10001 >
b10001 .
b0 (
b0 1
b0 '
b0 0
0,
0$
#415000
1$
#420000
b10100000000000000000000000010001 (
b10100000000000000000000000010001 1
b10001 '
b10001 0
1,
0$
#425000
1$
#430000
b10100000000000000000000000010010 ?
b10010 >
b10010 .
b0 (
b0 1
b0 '
b0 0
0,
0$
#435000
1$
#440000
b10100000000000000000000000010010 (
b10100000000000000000000000010010 1
b10010 '
b10010 0
1,
0$
#445000
1$
#450000
b10100000000000000000000000010011 ?
b10011 >
b10011 .
b0 (
b0 1
b0 '
b0 0
0,
0$
#455000
1$
#460000
b10100000000000000000000000010011 (
b10100000000000000000000000010011 1
b10011 '
b10011 0
1,
0$
#465000
1$
#470000
b10100000000000000000000000010100 ?
b10100 >
b10100 .
b0 (
b0 1
b0 '
b0 0
0,
0$
#475000
1$
#480000
b10100000000000000000000000010100 (
b10100000000000000000000000010100 1
b10100 '
b10100 0
1,
0$
#485000
1$
#490000
b10100000000000000000000000010101 ?
b10101 >
b10101 .
b0 (
b0 1
b0 '
b0 0
0,
0$
#495000
1$
#500000
b10100000000000000000000000010101 (
b10100000000000000000000000010101 1
b10101 '
b10101 0
1,
0$
#505000
1$
#510000
b10100000000000000000000000010110 ?
b10110 >
b10110 .
b0 (
b0 1
b0 '
b0 0
0,
0$
#515000
1$
#520000
b10100000000000000000000000010110 (
b10100000000000000000000000010110 1
b10110 '
b10110 0
1,
0$
#525000
1$
#530000
b10100000000000000000000000010111 ?
b10111 >
b10111 .
b0 (
b0 1
b0 '
b0 0
0,
0$
#535000
1$
#540000
b10100000000000000000000000010111 (
b10100000000000000000000000010111 1
b10111 '
b10111 0
1,
0$
#545000
1$
#550000
b10100000000000000000000000011000 ?
b11000 >
b11000 .
b0 (
b0 1
b0 '
b0 0
0,
0$
#555000
1$
#560000
b10100000000000000000000000011000 (
b10100000000000000000000000011000 1
b11000 '
b11000 0
1,
0$
#565000
1$
#570000
b10100000000000000000000000011001 ?
b11001 >
b11001 .
b0 (
b0 1
b0 '
b0 0
0,
0$
#575000
1$
#580000
b10100000000000000000000000011001 (
b10100000000000000000000000011001 1
b11001 '
b11001 0
1,
0$
#585000
1$
#590000
b10100000000000000000000000011010 ?
b11010 >
b11010 .
b0 (
b0 1
b0 '
b0 0
0,
0$
#595000
1$
#600000
b10100000000000000000000000011010 (
b10100000000000000000000000011010 1
b11010 '
b11010 0
1,
0$
#605000
1$
#610000
b10100000000000000000000000011011 ?
b11011 >
b11011 .
b0 (
b0 1
b0 '
b0 0
0,
0$
#615000
1$
#620000
b10100000000000000000000000011011 (
b10100000000000000000000000011011 1
b11011 '
b11011 0
1,
0$
#625000
1$
#630000
b10100000000000000000000000011100 ?
b11100 >
b11100 .
b0 (
b0 1
b0 '
b0 0
0,
0$
#635000
1$
#640000
b10100000000000000000000000011100 (
b10100000000000000000000000011100 1
b11100 '
b11100 0
1,
0$
#645000
1$
#650000
b10100000000000000000000000011101 ?
b11101 >
b11101 .
b0 (
b0 1
b0 '
b0 0
0,
0$
#655000
1$
#660000
b10100000000000000000000000011101 (
b10100000000000000000000000011101 1
b11101 '
b11101 0
1,
0$
#665000
1$
#670000
b10100000000000000000000000011110 ?
b11110 >
b11110 .
b0 (
b0 1
b0 '
b0 0
0,
0$
#675000
1$
#680000
b10100000000000000000000000011110 (
b10100000000000000000000000011110 1
b11110 '
b11110 0
1,
0$
#685000
1$
#690000
b10100000000000000000000000011111 ?
b11111 >
b11111 .
b0 (
b0 1
b0 '
b0 0
0,
0$
#695000
1$
#700000
b10100000000000000000000000011111 (
b10100000000000000000000000011111 1
b11111 '
b11111 0
1,
0$
#705000
1$
#710000
b10100000000000000000000000000001 "
b10100000000000000000000000000001 5
b1 )
b1 2
b1 :
b1 .
b0 (
b0 1
b0 '
b0 0
0,
0$
#711000
b10100000000000000000000000000010 "
b10100000000000000000000000000010 5
b10 )
b10 2
b10 :
b10 .
b100011 /
b11110000110100100100000011101110111001001101001011101000110010100101111011100100110010101100001011001000010000001110110011010010110000100100000011100100111001100110001 9
b10100000000000000000000000000001 7
b10100000000000000000000000000001 8
b10100000000000000000000000000001 %
b10100000000000000000000000000001 ;
#712000
b10100000000000000000000000000011 "
b10100000000000000000000000000011 5
b11 )
b11 2
b11 :
b11 .
b100100 /
b10100000000000000000000000000010 7
b10100000000000000000000000000010 8
b10100000000000000000000000000010 %
b10100000000000000000000000000010 ;
#713000
b10100000000000000000000000000100 "
b10100000000000000000000000000100 5
b100 )
b100 2
b100 :
b100 .
b100101 /
b10100000000000000000000000000011 7
b10100000000000000000000000000011 8
b10100000000000000000000000000011 %
b10100000000000000000000000000011 ;
#714000
b10100000000000000000000000000101 "
b10100000000000000000000000000101 5
b101 )
b101 2
b101 :
b101 .
b100110 /
b10100000000000000000000000000100 7
b10100000000000000000000000000100 8
b10100000000000000000000000000100 %
b10100000000000000000000000000100 ;
#715000
b10100000000000000000000000000110 "
b10100000000000000000000000000110 5
b110 )
b110 2
b110 :
b110 .
b100111 /
b10100000000000000000000000000101 7
b10100000000000000000000000000101 8
b10100000000000000000000000000101 %
b10100000000000000000000000000101 ;
1$
#716000
b10100000000000000000000000000111 "
b10100000000000000000000000000111 5
b111 )
b111 2
b111 :
b111 .
b101000 /
b10100000000000000000000000000110 7
b10100000000000000000000000000110 8
b10100000000000000000000000000110 %
b10100000000000000000000000000110 ;
#717000
b10100000000000000000000000001000 "
b10100000000000000000000000001000 5
b1000 )
b1000 2
b1000 :
b1000 .
b101001 /
b10100000000000000000000000000111 7
b10100000000000000000000000000111 8
b10100000000000000000000000000111 %
b10100000000000000000000000000111 ;
#718000
b10100000000000000000000000001001 "
b10100000000000000000000000001001 5
b1001 )
b1001 2
b1001 :
b1001 .
b101010 /
b10100000000000000000000000001000 7
b10100000000000000000000000001000 8
b10100000000000000000000000001000 %
b10100000000000000000000000001000 ;
#719000
b10100000000000000000000000001010 "
b10100000000000000000000000001010 5
b1010 )
b1010 2
b1010 :
b1010 .
b101011 /
b10100000000000000000000000001001 7
b10100000000000000000000000001001 8
b10100000000000000000000000001001 %
b10100000000000000000000000001001 ;
#720000
b10100000000000000000000000001011 "
b10100000000000000000000000001011 5
b1011 )
b1011 2
b1011 :
b1011 .
b101100 /
b10100000000000000000000000001010 7
b10100000000000000000000000001010 8
b10100000000000000000000000001010 %
b10100000000000000000000000001010 ;
0$
#721000
b10100000000000000000000000001100 "
b10100000000000000000000000001100 5
b1100 )
b1100 2
b1100 :
b1100 .
b101101 /
b10100000000000000000000000001011 7
b10100000000000000000000000001011 8
b10100000000000000000000000001011 %
b10100000000000000000000000001011 ;
#722000
b10100000000000000000000000001101 "
b10100000000000000000000000001101 5
b1101 )
b1101 2
b1101 :
b1101 .
b101110 /
b10100000000000000000000000001100 7
b10100000000000000000000000001100 8
b10100000000000000000000000001100 %
b10100000000000000000000000001100 ;
#723000
b10100000000000000000000000001110 "
b10100000000000000000000000001110 5
b1110 )
b1110 2
b1110 :
b1110 .
b101111 /
b10100000000000000000000000001101 7
b10100000000000000000000000001101 8
b10100000000000000000000000001101 %
b10100000000000000000000000001101 ;
#724000
b10100000000000000000000000001111 "
b10100000000000000000000000001111 5
b1111 )
b1111 2
b1111 :
b1111 .
b110000 /
b10100000000000000000000000001110 7
b10100000000000000000000000001110 8
b10100000000000000000000000001110 %
b10100000000000000000000000001110 ;
#725000
b10100000000000000000000000010000 "
b10100000000000000000000000010000 5
b10000 )
b10000 2
b10000 :
b10000 .
b110001 /
b10100000000000000000000000001111 7
b10100000000000000000000000001111 8
b10100000000000000000000000001111 %
b10100000000000000000000000001111 ;
1$
#726000
b10100000000000000000000000010001 "
b10100000000000000000000000010001 5
b10001 )
b10001 2
b10001 :
b10001 .
b110010 /
b10100000000000000000000000010000 7
b10100000000000000000000000010000 8
b10100000000000000000000000010000 %
b10100000000000000000000000010000 ;
#727000
b10100000000000000000000000010010 "
b10100000000000000000000000010010 5
b10010 )
b10010 2
b10010 :
b10010 .
b110011 /
b10100000000000000000000000010001 7
b10100000000000000000000000010001 8
b10100000000000000000000000010001 %
b10100000000000000000000000010001 ;
#728000
b10100000000000000000000000010011 "
b10100000000000000000000000010011 5
b10011 )
b10011 2
b10011 :
b10011 .
b110100 /
b10100000000000000000000000010010 7
b10100000000000000000000000010010 8
b10100000000000000000000000010010 %
b10100000000000000000000000010010 ;
#729000
b10100000000000000000000000010100 "
b10100000000000000000000000010100 5
b10100 )
b10100 2
b10100 :
b10100 .
b110101 /
b10100000000000000000000000010011 7
b10100000000000000000000000010011 8
b10100000000000000000000000010011 %
b10100000000000000000000000010011 ;
#730000
b10100000000000000000000000010101 "
b10100000000000000000000000010101 5
b10101 )
b10101 2
b10101 :
b10101 .
b110110 /
b10100000000000000000000000010100 7
b10100000000000000000000000010100 8
b10100000000000000000000000010100 %
b10100000000000000000000000010100 ;
0$
#731000
b10100000000000000000000000010110 "
b10100000000000000000000000010110 5
b10110 )
b10110 2
b10110 :
b10110 .
b110111 /
b10100000000000000000000000010101 7
b10100000000000000000000000010101 8
b10100000000000000000000000010101 %
b10100000000000000000000000010101 ;
#732000
b10100000000000000000000000010111 "
b10100000000000000000000000010111 5
b10111 )
b10111 2
b10111 :
b10111 .
b111000 /
b10100000000000000000000000010110 7
b10100000000000000000000000010110 8
b10100000000000000000000000010110 %
b10100000000000000000000000010110 ;
#733000
b10100000000000000000000000011000 "
b10100000000000000000000000011000 5
b11000 )
b11000 2
b11000 :
b11000 .
b111001 /
b10100000000000000000000000010111 7
b10100000000000000000000000010111 8
b10100000000000000000000000010111 %
b10100000000000000000000000010111 ;
#734000
b10100000000000000000000000011001 "
b10100000000000000000000000011001 5
b11001 )
b11001 2
b11001 :
b11001 .
b111010 /
b10100000000000000000000000011000 7
b10100000000000000000000000011000 8
b10100000000000000000000000011000 %
b10100000000000000000000000011000 ;
#735000
b10100000000000000000000000011010 "
b10100000000000000000000000011010 5
b11010 )
b11010 2
b11010 :
b11010 .
b111011 /
b10100000000000000000000000011001 7
b10100000000000000000000000011001 8
b10100000000000000000000000011001 %
b10100000000000000000000000011001 ;
1$
#736000
b10100000000000000000000000011011 "
b10100000000000000000000000011011 5
b11011 )
b11011 2
b11011 :
b11011 .
b111100 /
b10100000000000000000000000011010 7
b10100000000000000000000000011010 8
b10100000000000000000000000011010 %
b10100000000000000000000000011010 ;
#737000
b10100000000000000000000000011100 "
b10100000000000000000000000011100 5
b11100 )
b11100 2
b11100 :
b11100 .
b111101 /
b10100000000000000000000000011011 7
b10100000000000000000000000011011 8
b10100000000000000000000000011011 %
b10100000000000000000000000011011 ;
