Lab3/dff_rg.v
module dff_rg #(parameter WIDTH=18)(
    input clk,
    input rst,
    input [WIDTH-1:0] d,
    output reg [WIDTH-1:0] q
);

    always @(posedge clk or posedge rst) begin
        if (rst)
            q <= 0;
        else
            q <= d;
    end

endmodule

Lab3/inverse_function.v
module inverse_function #(
    parameter WIDTH = 18,
    parameter FRAC  = 14
)(
    input clk,
    input rst,
    input start,
    input  [WIDTH-1:0] D,
    output [WIDTH-1:0] x_out
);

    localparam ONE = (1 << FRAC);
    localparam TWO = (2 << FRAC);

    reg [WIDTH-1:0] x_reg;
    wire [WIDTH-1:0] x_next;

    assign x_out = x_reg;

    // x * D
    wire [2*WIDTH-1:0] mult1;
    assign mult1 = x_reg * D;

    wire [WIDTH-1:0] xD = mult1 >> FRAC;

    // 2 - xD
    wire [WIDTH-1:0] sub = TWO - xD;

    // x * (2 - xD)
    wire [2*WIDTH-1:0] mult2;
    assign mult2 = x_reg * sub;

    assign x_next = mult2 >> FRAC;

    always @(posedge clk or posedge rst) begin
        if (rst)
            x_reg <= 0;
        else if (start)
            x_reg <= ONE;
        else
            x_reg <= x_next;
    end

endmodule

Lab3/normalize_q4_14.v
module normalize_q4_14 (
    input  [17:0] D_in,
    output reg [17:0] D_norm,
    output reg [4:0] shift_count
);

    localparam HALF = 18'd8192;

    integer i;

    always @(*) begin
        D_norm = D_in;
        shift_count = 0;

        for (i = 0; i < 17; i = i + 1) begin
            if (D_norm < HALF) begin
                D_norm = D_norm << 1;
                shift_count = shift_count + 1;
            end
        end
    end

endmodule

Lab3/division_newton.v
module division_newton #(
    parameter DIV_WIDTH = 36,
    parameter WIDTH     = 18,
    parameter FRAC      = 14
)(
    input clk,
    input rst,
    input start,
    input  [DIV_WIDTH-1:0] dividend,   // Q22.14
    input  [WIDTH-1:0]     divisor,    // Q4.14
    output [WIDTH-1:0]     quotient    // Q4.14
);

    // Registers
    wire [DIV_WIDTH-1:0] dividend_reg;
    wire [WIDTH-1:0] divisor_reg;

    dff_rg #(DIV_WIDTH) REG_A (
        .clk(clk),
        .rst(rst),
        .d(dividend),
        .q(dividend_reg)
    );

    dff_rg #(WIDTH) REG_D (
        .clk(clk),
        .rst(rst),
        .d(divisor),
        .q(divisor_reg)
    );

    // Normalize
    wire [WIDTH-1:0] D_norm;
    wire [4:0] shift_count;

    normalize_q4_14 NORM (
        .D_in(divisor_reg),
        .D_norm(D_norm),
        .shift_count(shift_count)
    );

    // Inverse
    wire [WIDTH-1:0] inverse_out;

    inverse_function #(WIDTH, FRAC) INV (
        .clk(clk),
        .rst(rst),
        .start(start),
        .D(D_norm),
        .x_out(inverse_out)
    );

    // Multiply 36 × 18
    wire [DIV_WIDTH+WIDTH-1:0] mult_full;
    assign mult_full = dividend_reg * inverse_out;

    // Return to Q22.14
    wire [DIV_WIDTH+WIDTH-1:0] mult_scaled;
    assign mult_scaled = mult_full >> FRAC;

    // Compensate normalization
    wire [DIV_WIDTH+WIDTH-1:0] corrected;
    assign corrected = mult_scaled >> shift_count;

    // Take lower 18 bits as Q4.14 result
    dff_rg #(WIDTH) OUT_REG (
        .clk(clk),
        .rst(rst),
        .d(corrected[WIDTH-1:0]),
        .q(quotient)
    );

endmodule

Lab3/division_newton_tb.v
`timescale 1ns / 1ps

module division_newton_tb;

    parameter DIV_WIDTH = 36;
    parameter WIDTH     = 18;
    parameter FRAC      = 14;
    parameter WAIT_CYCLES = 12;

    reg clk;
    reg rst;
    reg start;

    reg  [DIV_WIDTH-1:0] dividend;   // Q22.14
    reg  [WIDTH-1:0]     divisor;    // Q4.14
    wire [WIDTH-1:0]     quotient;   // Q4.14

    // DUT
    division_newton #(
        .DIV_WIDTH(DIV_WIDTH),
        .WIDTH(WIDTH),
        .FRAC(FRAC)
    ) DUT (
        .clk(clk),
        .rst(rst),
        .start(start),
        .dividend(dividend),
        .divisor(divisor),
        .quotient(quotient)
    );

    // Clock
    always #5 clk = ~clk;

    // ----------------------------
    // Conversion Functions
    // ----------------------------

    function real fixed_to_real_18;
        input [WIDTH-1:0] value;
        begin
            fixed_to_real_18 = value / (2.0**FRAC);
        end
    endfunction

    function real fixed_to_real_36;
        input [DIV_WIDTH-1:0] value;
        begin
            fixed_to_real_36 = value / (2.0**FRAC);
        end
    endfunction

    function [WIDTH-1:0] real_to_fixed_18;
        input real value;
        begin
            real_to_fixed_18 = $rtoi(value * (2.0**FRAC));
        end
    endfunction

    function [DIV_WIDTH-1:0] real_to_fixed_36;
        input real value;
        begin
            real_to_fixed_36 = $rtoi(value * (2.0**FRAC));
        end
    endfunction

    real expected;
    real result;

    task run_test;
        input real A_real;
        input real D_real;
        begin
            dividend = real_to_fixed_36(A_real);
            divisor  = real_to_fixed_18(D_real);

            expected = A_real / D_real;

            @(posedge clk);
            start = 1;
            @(posedge clk);
            start = 0;

            repeat (WAIT_CYCLES) @(posedge clk);

            result = fixed_to_real_18(quotient);

            $display("--------------------------------------");
            $display("A = %f , D = %f", A_real, D_real);
            $display("Expected = %f", expected);
            $display("DUT      = %f", result);
            $display("Error    = %f", expected - result);
        end
    endtask

    initial begin
        $dumpfile("division_newton_sim.vcd");
        $dumpvars(0,division_newton_tb);
        clk = 0;
        rst = 1;
        start = 0;

        #20 rst = 0;

        $display("======================================");
        $display("  Newton Divider Testbench    ");
        $display("======================================");

        // Small controlled cases
        run_test(10, 2.6);   // expected 4.0
        run_test(2.5, 2.5);    // expected 5.0
        run_test(8.6, 2.5);    // expected 2.5

        $display("======================================");
        $display("Test Finished");
        $display("======================================");

        $finish;
    end

endmodule

Lab3/division_newton_sim.vcd
$date
	Tue Mar  3 12:16:55 2026
$end
$version
	Icarus Verilog
$end
$timescale
	1ps
$end
$scope module division_newton_tb $end
$var wire 18 ! quotient [17:0] $end
$var parameter 32 " DIV_WIDTH $end
$var parameter 32 # FRAC $end
$var parameter 32 $ WAIT_CYCLES $end
$var parameter 32 % WIDTH $end
$var reg 1 & clk $end
$var reg 36 ' dividend [35:0] $end
$var reg 18 ( divisor [17:0] $end
$var reg 1 ) rst $end
$var reg 1 * start $end
$var real 1 + expected $end
$var real 1 , result $end
$scope function fixed_to_real_18 $end
$var reg 18 - value [17:0] $end
$upscope $end
$scope function fixed_to_real_36 $end
$var reg 36 . value [35:0] $end
$upscope $end
$scope function real_to_fixed_18 $end
$var real 1 / value $end
$upscope $end
$scope function real_to_fixed_36 $end
$var real 1 0 value $end
$upscope $end
$scope module DUT $end
$var wire 1 & clk $end
$var wire 36 1 dividend [35:0] $end
$var wire 18 2 divisor [17:0] $end
$var wire 1 ) rst $end
$var wire 1 * start $end
$var wire 5 3 shift_count [4:0] $end
$var wire 18 4 quotient [17:0] $end
$var wire 54 5 mult_scaled [53:0] $end
$var wire 54 6 mult_full [53:0] $end
$var wire 18 7 inverse_out [17:0] $end
$var wire 18 8 divisor_reg [17:0] $end
$var wire 36 9 dividend_reg [35:0] $end
$var wire 54 : corrected [53:0] $end
$var wire 18 ; D_norm [17:0] $end
$var parameter 32 < DIV_WIDTH $end
$var parameter 32 = FRAC $end
$var parameter 32 > WIDTH $end
$scope module INV $end
$var wire 1 & clk $end
$var wire 1 ) rst $end
$var wire 1 * start $end
$var wire 18 ? x_out [17:0] $end
$var wire 18 @ x_next [17:0] $end
$var wire 18 A xD [17:0] $end
$var wire 18 B sub [17:0] $end
$var wire 36 C mult2 [35:0] $end
$var wire 36 D mult1 [35:0] $end
$var wire 18 E D [17:0] $end
$var parameter 32 F FRAC $end
$var parameter 46 G ONE $end
$var parameter 46 H TWO $end
$var parameter 32 I WIDTH $end
$var reg 18 J x_reg [17:0] $end
$upscope $end
$scope module NORM $end
$var wire 18 K D_in [17:0] $end
$var parameter 18 L HALF $end
$var reg 18 M D_norm [17:0] $end
$var reg 5 N shift_count [4:0] $end
$var integer 32 O i [31:0] $end
$upscope $end
$scope module OUT_REG $end
$var wire 1 & clk $end
$var wire 18 P d [17:0] $end
$var wire 1 ) rst $end
$var parameter 32 Q WIDTH $end
$var reg 18 R q [17:0] $end
$upscope $end
$scope module REG_A $end
$var wire 1 & clk $end
$var wire 36 S d [35:0] $end
$var wire 1 ) rst $end
$var parameter 32 T WIDTH $end
$var reg 36 U q [35:0] $end
$upscope $end
$scope module REG_D $end
$var wire 1 & clk $end
$var wire 18 V d [17:0] $end
$var wire 1 ) rst $end
$var parameter 32 W WIDTH $end
$var reg 18 X q [17:0] $end
$upscope $end
$upscope $end
$scope task run_test $end
$var real 1 Y A_real $end
$var real 1 Z D_real $end
$upscope $end
$upscope $end
$enddefinitions $end
$comment Show the parameter values. $end
$dumpall
b10010 W
b100100 T
b10010 Q
b10000000000000 L
b10010 I
b1000000000000000 H
b100000000000000 G
b1110 F
b10010 >
b1110 =
b100100 <
b10010 %
b1100 $
b1110 #
b100100 "
$end
#0
$dumpvars
r0 Z
r0 Y
b0 X
bx V
b0 U
bx S
b0 R
b0 P
b10001 O
b10001 N
b0 M
b0 K
b0 J
b0 E
b0 D
b0 C
b1000000000000000 B
b0 A
b0 @
b0 ?
b0 ;
b0 :
b0 9
b0 8
b0 7
b0 6
b0 5
b0 4
b10001 3
bx 2
bx 1
r0 0
r0 /
bx .
bx -
r0 ,
r0 +
0*
1)
bx (
bx '
0&
b0 !
$end
#5000
1&
#10000
0&
#15000
1&
#20000
0&
r3.846153846153846 +
b1010011001100110 (
b1010011001100110 2
b1010011001100110 V
r2.6 /
b101000000000000000 '
b101000000000000000 1
b101000000000000000 S
r10 0
r2.6 Z
r10 Y
0)
#25000
b111101100110011010 B
b1010011001100110 A
b111101100110011010 @
b101000000000000000 P
b101000000000000000 :
b101000000000000000 5
b101001100110011000000000000000 D
b11110110011001101000000000000000 C
b10100000000000000000000000000000 6
b10001 O
b0 3
b0 N
b1010011001100110 ;
b1010011001100110 E
b1010011001100110 M
b100000000000000 7
b100000000000000 ?
b100000000000000 J
b1010011001100110 8
b1010011001100110 K
b1010011001100110 X
b101000000000000000 9
b101000000000000000 U
1*
1&
#30000
0&
#35000
b100111110101110110 B
b100000001010001010 A
b100101100011101001 @
b101000000000000100 P
b1001101000000000000100 :
b1001101000000000000100 5
b1010000000101000101000111101011100 D
b100110010110001110100111111011111100 C
b100110100000000000010000000000000000 6
b111101100110011010 7
b111101100110011010 ?
b111101100110011010 J
b101000000000000000 !
b101000000000000000 4
b101000000000000000 R
0*
1&
#40000
0&
#45000
b100110010110100110 B
b100001101001011010 A
b101000000110101110 @
b110111100100011010 P
b101110111100100011010 :
b101110111100100011010 5
b110000110100101101000001011010110 D
b10110100000011010111001010000010110 C
b10111011110010001101000000000000000 6
b101000000000000100 !
b101000000000000100 4
b101000000000000100 R
b100101100011101001 7
b100101100011101001 ?
b100101100011101001 J
1&
#50000
0&
#55000
b11111101110100111 B
b101000010001011001 A
b111110000111011000 @
b10001000011001100 P
b110010001000011001100 :
b110010001000011001100 5
b110100001000101100111111101010100 D
b10011111000011101100011001010000010 C
b11001000100001100110000000000000000 6
b101000000110101110 7
b101000000110101110 ?
b101000000110101110 J
b110111100100011010 !
b110111100100011010 4
b110111100100011010 R
1&
#60000
0&
#65000
b100110100000001000 B
b100001011111111000 A
b10101111000111011 @
b101101001001110000 P
b1001101101001001110000 :
b1001101101001001110000 5
b1010000101111111100000110000010000 D
b100101010111100011101100111011000000 C
b100110110100100111000000000000000000 6
b10001000011001100 !
b10001000011001100 4
b10001000011001100 R
b111110000111011000 7
b111110000111011000 ?
b111110000111011000 J
1&
#70000
0&
#75000
b1111000101101001 B
b111000111010010111 A
b10010100100010100 @
b11010111001001110 P
b11011010111001001110 :
b11011010111001001110 5
b11100011101001011100110110000010 D
b101001010010001010011000100110011 C
b1101101011100100111000000000000000 6
b10101111000111011 7
b10101111000111011 ?
b10101111000111011 J
b101101001001110000 !
b101101001001110000 4
b101101001001110000 R
1&
#80000
0&
#85000
b10111101110011011 B
b110000010001100101 A
b101110001000010001 @
b111001101011001000 P
b10111001101011001000 :
b10111001101011001000 5
b11000001000110010101010111111000 D
b110111000100001000111101100011100 C
b1011100110101100100000000000000000 6
b11010111001001110 !
b11010111001001110 4
b11010111001001110 R
b10010100100010100 7
b10010100100010100 ?
b10010100100010100 J
1&
#90000
0&
#95000
b10000000100001100 B
b110111111011110100 A
b111001010001010110 @
b1101010010101010 P
b111001101010010101010 :
b111001101010010101010 5
b111011111101111010001100011000110 D
b1011100101000101011010100111001100 C
b11100110101001010101000000000000000 6
b101110001000010001 7
b101110001000010001 ?
b101110001000010001 J
b111001101011001000 !
b111001101011001000 4
b111001101011001000 R
1&
#100000
0&
#105000
b110011000110001101 B
b10100111001110011 A
b11011100101111100 @
b111100101101011100 P
b1000111100101101011100 :
b1000111100101101011100 5
b1001010011100111001101111001000100 D
b101101101110010111110010100101011110 C
b100011110010110101110000000000000000 6
b1101010010101010 !
b1101010010101010 4
b1101010010101010 R
b111001010001010110 7
b111001010001010110 ?
b111001010001010110 J
1&
#110000
0&
#115000
b10000100111 B
b111101111011001 A
b1110010100100 @
b10011111011011000 P
b100010011111011011000 :
b100010011111011011000 5
b100011110111101100100111101101000 D
b111001010010011000111100100 C
b10001001111101101100000000000000000 6
b11011100101111100 7
b11011100101111100 ?
b11011100101111100 J
b111100101101011100 !
b111100101101011100 4
b111100101101011100 R
1&
#120000
0&
#125000
b11010110001001 B
b100101001110111 A
b1011111110101 @
b10001111001101000 P
b10001111001101000 :
b10001111001101000 5
b10010100111011100000101011000 D
b101111111010100011111000100 C
b1000111100110100000000000000000 6
b10011111011011000 !
b10011111011011000 4
b10011111011011000 R
b1110010100100 7
b1110010100100 ?
b1110010100100 J
1&
#130000
0&
#135000
b100000110110111 B
b11111001001001 A
b1100010011001 @
b1110111110010010 P
b1110111110010010 :
b1110111110010010 5
b1111100100100110100110011110 D
b110001001100101010100100011 C
b111011111001001000000000000000 6
b1011111110101 7
b1011111110101 ?
b1011111110101 J
b10001111001101000 !
b10001111001101000 4
b10001111001101000 R
1&
#140000
0&
#145000
b100000000001100 B
b11111111110100 A
b1100010011101 @
b1111010111111010 P
b1111010111111010 :
b1111010111111010 5
b1111111111010000001011110110 D
b110001001110110011100101100 C
b111101011111101000000000000000 6
b1110111110010010 !
b1110111110010010 4
b1110111110010010 R
b1100010011001 7
b1100010011001 ?
b1100010011001 J
1&
#150000
0&
#155000
b100001001111000 B
b11110110001000 A
b1100110010000 @
b11110110001000 P
b11110110001000 :
b11110110001000 5
b10001 O
b1010000000000000 ;
b1010000000000000 E
b1010000000000000 M
b1111011000100010000000000000 D
b110011001000000001110011000 C
b1111011000100010000000000000 6
b1010000000000000 9
b1010000000000000 U
b1010000000000000 8
b1010000000000000 K
b1010000000000000 X
b1100010011101 7
b1100010011101 ?
b1100010011101 J
b1111010111111010 !
b1111010111111010 4
b1111010111111010 R
r1 +
b1010000000000000 (
b1010000000000000 2
b1010000000000000 V
r2.5 /
b1010000000000000 '
b1010000000000000 1
b1010000000000000 S
r2.5 0
r2.5 Z
r2.5 Y
r3.7432861328125 ,
b1110111110010010 -
1&
#160000
0&
#165000
b111110000000000000 B
b1010000000000000 A
b111110000000000000 @
b1010000000000000 P
b1010000000000000 :
b1010000000000000 5
b101000000000000000000000000000 D
b11111000000000000000000000000000 C
b101000000000000000000000000000 6
b11110110001000 !
b11110110001000 4
b11110110001000 R
b100000000000000 7
b100000000000000 ?
b100000000000000 J
1*
1&
#170000
0&
#175000
b101101000000000000 B
b11011000000000000 A
b111001100000000000 @
b11011000000000000 P
b10011011000000000000 :
b10011011000000000000 5
b1001101100000000000000000000000000 D
b101011100110000000000000000000000000 C
b1001101100000000000000000000000000 6
b111110000000000000 7
b111110000000000000 ?
b111110000000000000 J
b1010000000000000 !
b1010000000000000 4
b1010000000000000 R
0*
1&
#180000
0&
#185000
b111000010000000000 B
b1111110000000000 A
b101000100110000000 @
b1111110000000000 P
b10001111110000000000 :
b10001111110000000000 5
b1000111111000000000000000000000000 D
b110010100010011000000000000000000000 C
b1000111111000000000000000000000000 6
b11011000000000000 !
b11011000000000000 4
b11011000000000000 R
b111001100000000000 7
b111001100000000000 ?
b111001100000000000 J
1&
#190000
0&
#195000
b100010100001000000 B
b100101011111000000 A
b11110010001111001 @
b100101011111000000 P
b1100101011111000000 :
b1100101011111000000 5
b110010101111100000000000000000000 D
b10101111001000111100110000000000000 C
b110010101111100000000000000000000 6
b101000100110000000 7
b101000100110000000 ?
b101000100110000000 J
b1111110000000000 !
b1111110000000000 4
b1111110000000000 R
1&
#200000
0&
#205000
b111100010011010010 B
b1011101100101110 A
b1000011110010100 @
b1011101100101110 P
b1001011101100101110 :
b1001011101100101110 5
b100101110110010111010000000000000 D
b11100100001111001010000111101000010 C
b100101110110010111010000000000000 6
b100101011111000000 !
b100101011111000000 4
b100101011111000000 R
b11110010001111001 7
b11110010001111001 ?
b11110010001111001 J
1&
#210000
0&
#215000
b110010110100001110 B
b10101001011110010 A
b101011101001100001 @
b10101001011110010 P
b10101001011110010 :
b10101001011110010 5
b1010100101111001000000000000000 D
b110101110100110000110111000011000 C
b1010100101111001000000000000000 6
b1000011110010100 7
b1000011110010100 ?
b1000011110010100 J
b1011101100101110 !
b1011101100101110 4
b1011101100101110 R
1&
#220000
0&
#225000
b11010111000001110 B
b101101000111110010 A
b100101010011010100 @
b101101000111110010 P
b1101101000111110010 :
b1101101000111110010 5
b110110100011111001010000000000000 D
b10010010101001101010001111101001110 C
b110110100011111001010000000000000 6
b10101001011110010 !
b10101001011110010 4
b10101001011110010 R
b101011101001100001 7
b101011101001100001 ?
b101011101001100001 J
1&
#230000
0&
#235000
b101010101111101110 B
b11101010000010010 A
b1110100111110001 @
b11101010000010010 P
b1011101010000010010 :
b1011101010000010010 5
b101110101000001001000000000000000 D
b11000111010011111000111100100011000 C
b101110101000001001000000000000000 6
b100101010011010100 7
b100101010011010100 ?
b100101010011010100 J
b101101000111110010 !
b101101000111110010 4
b101101000111110010 R
1&
#240000
0&
#245000
b100011011100100110 B
b100100100011011010 A
b1100100011110 @
b100100100011011010 P
b100100100011011010 :
b100100100011011010 5
b10010010001101101010000000000000 D
b1000000110010001111000000011000110 C
b10010010001101101010000000000000 6
b11101010000010010 !
b11101010000010010 4
b11101010000010010 R
b1110100111110001 7
b1110100111110001 ?
b1110100111110001 J
1&
#250000
0&
#255000
b100000100110101 B
b11111011001011 A
b1100110010111 @
b11111011001011 P
b11111011001011 :
b11111011001011 5
b1111101100101100000000000000 D
b110011001011101000100110110 C
b1111101100101100000000000000 6
b1100100011110 7
b1100100011110 ?
b1100100011110 J
b100100100011011010 !
b100100100011011010 4
b100100100011011010 R
1&
#260000
0&
#265000
b100000000000111 B
b11111111111001 A
b1100110011001 @
b11111111111001 P
b11111111111001 :
b11111111111001 5
b1111111111100110000000000000 D
b110011001100111001100100001 C
b1111111111100110000000000000 6
b11111011001011 !
b11111011001011 4
b11111011001011 R
b1100110010111 7
b1100110010111 ?
b1100110010111 J
1&
#270000
0&
#275000
b100000000000010 B
b11111111111110 A
b1100110011001 @
b11111111111110 P
b11111111111110 :
b11111111111110 5
b1111111111111010000000000000 D
b110011001100111001100110010 C
b1111111111111010000000000000 6
b1100110011001 7
b1100110011001 ?
b1100110011001 J
b11111111111001 !
b11111111111001 4
b11111111111001 R
1&
#280000
0&
#285000
b11111111111110 !
b11111111111110 4
b11111111111110 R
1&
#290000
0&
#295000
b1101110000100011 P
b1101110000100011 :
b1101110000100011 5
b110111000010001110100011110110 6
b100010011001100110 9
b100010011001100110 U
r3.44 +
b100010011001100110 '
b100010011001100110 1
b100010011001100110 S
r8.6 0
r8.6 Y
r0.9998779296875 ,
b11111111111110 -
1&
#300000
0&
#305000
b111110000000000000 B
b1010000000000000 A
b111110000000000000 @
b100010011001100110 P
b100010011001100110 :
b100010011001100110 5
b101000000000000000000000000000 D
b11111000000000000000000000000000 C
b10001001100110011000000000000000 6
b1101110000100011 !
b1101110000100011 4
b1101110000100011 R
b100000000000000 7
b100000000000000 ?
b100000000000000 J
1*
1&
#310000
0&
#315000
b101101000000000000 B
b11011000000000000 A
b111001100000000000 @
b10101001100101101 P
b1000010101001100101101 :
b1000010101001100101101 5
b1001101100000000000000000000000000 D
b101011100110000000000000000000000000 C
b100001010100110010110100000000000000 6
b111110000000000000 7
b111110000000000000 ?
b111110000000000000 J
b100010011001100110 !
b100010011001100110 4
b100010011001100110 R
0*
1&
#320000
0&
#325000
b111000010000000000 B
b1111110000000000 A
b101000100110000000 @
b101110011111111010 P
b111101110011111111010 :
b111101110011111111010 5
b1000111111000000000000000000000000 D
b110010100010011000000000000000000000 C
b11110111001111111101001000000000000 6
b10101001100101101 !
b10101001100101101 4
b10101001100101101 R
b111001100000000000 7
b111001100000000000 ?
b111001100000000000 J
1&
#330000
0&
#335000
b100010100001000000 B
b100101011111000000 A
b11110010001111001 @
b11101000110101111 P
b101011101000110101111 :
b101011101000110101111 5
b110010101111100000000000000000000 D
b10101111001000111100110000000000000 C
b10101110100011010111100100100000000 6
b101000100110000000 7
b101000100110000000 ?
b101000100110000000 J
b101110011111111010 !
b101110011111111010 4
b101110011111111010 R
1&
#340000
0&
#345000
b111100010011010010 B
b1011101100101110 A
b1000011110010100 @
b100011001110011 P
b100000100011001110011 :
b100000100011001110011 5
b100101110110010111010000000000000 D
b11100100001111001010000111101000010 C
b10000010001100111001111111000110110 6
b11101000110101111 !
b11101000110101111 4
b11101000110101111 R
b11110010001111001 7
b11110010001111001 ?
b11110010001111001 J
1&
#350000
0&
#355000
b110010110100001110 B
b10101001011110010 A
b101011101001100001 @
b1000110111110111 P
b1001000110111110111 :
b1001000110111110111 5
b1010100101111001000000000000000 D
b110101110100110000110111000011000 C
b100100011011111011111110011111000 6
b1000011110010100 7
b1000011110010100 ?
b1000011110010100 J
b100011001110011 !
b100011001110011 4
b100011001110011 R
1&
#360000
0&
#365000
b11010111000001110 B
b101101000111110010 A
b100101010011010100 @
b110111011000001010 P
b101110111011000001010 :
b101110111011000001010 5
b110110100011111001010000000000000 D
b10010010101001101010001111101001110 C
b10111011101100000101010100010100110 6
b1000110111110111 !
b1000110111110111 4
b1000110111110111 R
b101011101001100001 7
b101011101001100001 ?
b101011101001100001 J
1&
#370000
0&
#375000
b101010101111101110 B
b11101010000010010 A
b1110100111110001 @
b110010110101 P
b101000000110010110101 :
b101000000110010110101 5
b101110101000001001000000000000000 D
b11000111010011111000111100100011000 C
b10100000011001011010100010001111000 6
b100101010011010100 7
b100101010011010100 ?
b100101010011010100 J
b110111011000001010 !
b110111011000001010 4
b110111011000001010 R
1&
#380000
0&
#385000
b100011011100100110 B
b100100100011011010 A
b1100100011110 @
b111101101111100011 P
b1111101101111100011 :
b1111101101111100011 5
b10010010001101101010000000000000 D
b1000000110010001111000000011000110 C
b111110110111110001111110000000110 6
b110010110101 !
b110010110101 4
b110010110101 R
b1110100111110001 7
b1110100111110001 ?
b1110100111110001 J
1&
#390000
0&
#395000
b100000100110101 B
b11111011001011 A
b1100110010111 @
b1101100000000001 P
b1101100000000001 :
b1101100000000001 5
b1111101100101100000000000000 D
b110011001011101000100110110 C
b110110000000000111010111110100 6
b1100100011110 7
b1100100011110 ?
b1100100011110 J
b111101101111100011 !
b111101101111100011 4
b111101101111100011 R
1&
#400000
0&
#405000
b100000000000111 B
b11111111111001 A
b1100110011001 @
b1101110000010010 P
b1101110000010010 :
b1101110000010010 5
b1111111111100110000000000000 D
b110011001100111001100100001 C
b110111000001001001110000101010 6
b1101100000000001 !
b1101100000000001 4
b1101100000000001 R
b1100110010111 7
b1100110010111 ?
b1100110010111 J
1&
#410000
0&
#415000
b100000000000010 B
b11111111111110 A
b1100110011001 @
b1101110000100011 P
b1101110000100011 :
b1101110000100011 5
b1111111111111010000000000000 D
b110011001100111001100110010 C
b110111000010001110100011110110 6
b1100110011001 7
b1100110011001 ?
b1100110011001 J
b1101110000010010 !
b1101110000010010 4
b1101110000010010 R
1&
#420000
0&
#425000
b1101110000100011 !
b1101110000100011 4
b1101110000100011 R
1&
#430000
0&
#435000
r3.43963623046875 ,
b1101110000100011 -
1&
